jaskirat/DCT standalone_on_tb/iter3/iter3.srcs/sources_1/new/dct_dsp_module.v
`timescale 1ns / 1ps

module matrix_mult_8x8_dsp #(
    parameter TRANSPOSE_B = 0
) (
    input clk,
    input reset,
    input enable,
    input [1023:0] A, // 8x8 matrix, each element 16-bit Q11.5
    input [1023:0] B,
    output reg [1023:0] C,
    output reg done
);

    // 2D arrays for the matrices (signed Q11.5 numbers)
    reg signed [15:0] matA [0:7][0:7];
    reg signed [15:0] matB [0:7][0:7];
    // 32-bit accumulators in Q22.10 format (result of Q11.5*Q11.5 multiplication)
    reg signed [31:0] accum [0:7][0:7];

    // Control signals and states
    reg [3:0] k;  // dot product index
    reg [1:0] state;
    localparam IDLE    = 2'b00,
               LOAD    = 2'b01,
               COMPUTE = 2'b10,
               DONE_ST = 2'b11;
    integer i, j;

    // Load matrices from the 1024-bit bus into 2D arrays
    always @(posedge clk) begin
        if (state == LOAD) begin
            for (i = 0; i < 8; i = i + 1) begin
                for (j = 0; j < 8; j = j + 1) begin
                    matA[i][j] <= A[(i*8+j)*16 +: 16];
                    matB[i][j] <= B[(i*8+j)*16 +: 16];
                end
            end
        end
    end

    // Main state machine using DSP slices for MAC operations
    always @(posedge clk or posedge reset) begin
        if (reset) begin
            state <= IDLE;
            done <= 0;
            k <= 0;
            for (i = 0; i < 8; i = i + 1)
                for (j = 0; j < 8; j = j + 1)
                    accum[i][j] <= 32'd0;
        end else begin
            case (state)
                IDLE: if (enable) state <= LOAD;
                LOAD: begin
                    state <= COMPUTE;
                    k <= 0;
                end
                COMPUTE: begin
                    // 64 parallel multiply-accumulate operations.
                    // When multiplying two Q11.5 numbers, the product is Q22.10.
                    for (i = 0; i < 8; i = i + 1) begin
                        for (j = 0; j < 8; j = j + 1) begin
                            (* use_dsp48 = "yes" *)
                            if (TRANSPOSE_B)
                                accum[i][j] <= accum[i][j] + (matA[i][k] * matB[j][k]);
                            else
                                accum[i][j] <= accum[i][j] + (matA[i][k] * matB[k][j]);
                        end
                    end
                    if (k == 7) begin
                        state <= DONE_ST;
                        k <= 0;
                    end else begin
                        k <= k + 1;
                    end
                end
                DONE_ST: begin
                    // Convert from Q22.10 to Q11.5 by discarding 5 fractional bits.
                    // Here we select bits [20:5] of the accumulator for each element.
                    for (i = 0; i < 8; i = i + 1) begin
                        for (j = 0; j < 8; j = j + 1) begin
                            C[(i*8+j)*16 +: 16] <= accum[i][j][20:5];
                        end
                    end
                    done <= 1;
                    state <= IDLE;
                end
            endcase
        end
    end

endmodule

jaskirat/DCT standalone_on_tb/iter3/iter3.srcs/sources_1/new/top_mod_dct.v
`timescale 1ns / 1ps

module dct_top (
    input clk,
    input reset,
    input start,
    output reg done
);
    // Behavioral BRAMs (64 words of 16 bits each)
    reg [15:0] bram_X [0:63];    // Input X (and final result overwritten here)
    reg [15:0] bram_B2 [0:63];   // Intermediate storage: result of D*X
    reg [15:0] bram_D [0:63];    // DCT coefficient ROM

    // Wires for connecting to the multiplier modules
    reg [1023:0] mat_A;
    reg [1023:0] mat_B;
    wire [1023:0] mat_out;
    wire mult_done;

    // For the second multiplication
    reg [1023:0] inter_result;
    wire [1023:0] final_result;
    wire mult2_done;

    // Top-level state machine
    reg [1:0] state;
    localparam IDLE = 2'b00,
               MUL1 = 2'b01,
               MUL2 = 2'b10,
               DONE  = 2'b11;
    integer i;

    // Instantiate multiplier for stage 1: D * X (normal multiplication)
    matrix_mult_8x8_dsp #(.TRANSPOSE_B(0)) mult1 (
        .clk(clk),
        .reset(reset),
        .enable(state == MUL1),
        .A(mat_A), // will carry D (from bram_D)
        .B(mat_B), // will carry X (from bram_X)
        .C(mat_out),
        .done(mult_done)
    );

    // Instantiate multiplier for stage 2: (D*X) * D^T 
    matrix_mult_8x8_dsp #(.TRANSPOSE_B(1)) mult2 (
        .clk(clk),
        .reset(reset),
        .enable(state == MUL2),
        .A(inter_result), // intermediate result from stage 1
        .B(mat_B),        // will carry D (from bram_D)
        .C(final_result),
        .done(mult2_done)
    );

    // Pack the contents of the coefficient ROM (bram_D) into a 1024-bit bus
    // This bus is used as the A operand for mult1.
    always @(*) begin
        for(i = 0; i < 64; i = i + 1)
            mat_A[i*16 +: 16] = bram_D[i];
    end

    // For the B operand: In stage MUL1 we use X (from bram_X), and in stage MUL2 we use D (from bram_D)
    always @(*) begin
        if(state == MUL1)
            for(i = 0; i < 64; i = i + 1)
                mat_B[i*16 +: 16] = bram_X[i];
        else
            for(i = 0; i < 64; i = i + 1)
                mat_B[i*16 +: 16] = bram_D[i];
    end

    // Top-level state machine: control the two multiplications and the memory transfers.
    always @(posedge clk or posedge reset) begin
        if(reset) begin
            state <= IDLE;
            done <= 0;
            // Initialize coefficient ROM (bram_D) with values.
            // In practice, replace these dummy values with the output of your Python script.
//            for(i = 0; i < 64; i = i + 1)
//                bram_D[i] <= 16'h0100; // dummy value = 1.0 (Q8.8); update with real DCT coefficients
bram_D[0] <= 16'h000B; bram_D[1] <= 16'h000B; bram_D[2] <= 16'h000B; bram_D[3] <= 16'h000B; bram_D[4] <= 16'h000B; bram_D[5] <= 16'h000B; bram_D[6] <= 16'h000B; bram_D[7] <= 16'h000B; bram_D[8] <= 16'h0010; bram_D[9] <= 16'h000D; bram_D[10] <= 16'h0009; bram_D[11] <= 16'h0003; bram_D[12] <= 16'hFFFD; bram_D[13] <= 16'hFFF7; bram_D[14] <= 16'hFFF3; bram_D[15] <= 16'hFFF0; bram_D[16] <= 16'h000F; bram_D[17] <= 16'h0006; bram_D[18] <= 16'hFFFA; bram_D[19] <= 16'hFFF1; bram_D[20] <= 16'hFFF1; bram_D[21] <= 16'hFFFA; bram_D[22] <= 16'h0006; bram_D[23] <= 16'h000F; bram_D[24] <= 16'h000D; bram_D[25] <= 16'hFFFD; bram_D[26] <= 16'hFFF0; bram_D[27] <= 16'hFFF7; bram_D[28] <= 16'h0009; bram_D[29] <= 16'h0010; bram_D[30] <= 16'h0003; bram_D[31] <= 16'hFFF3; bram_D[32] <= 16'h000B; bram_D[33] <= 16'hFFF5; bram_D[34] <= 16'hFFF5; bram_D[35] <= 16'h000B; bram_D[36] <= 16'h000B; bram_D[37] <= 16'hFFF5; bram_D[38] <= 16'hFFF5; bram_D[39] <= 16'h000B; bram_D[40] <= 16'h0009; bram_D[41] <= 16'hFFF0; bram_D[42] <= 16'h0003; bram_D[43] <= 16'h000D; bram_D[44] <= 16'hFFF3; bram_D[45] <= 16'hFFFD; bram_D[46] <= 16'h0010; bram_D[47] <= 16'hFFF7; bram_D[48] <= 16'h0006; bram_D[49] <= 16'hFFF1; bram_D[50] <= 16'h000F; bram_D[51] <= 16'hFFFA; bram_D[52] <= 16'hFFFA; bram_D[53] <= 16'h000F; bram_D[54] <= 16'hFFF1; bram_D[55] <= 16'h0006; bram_D[56] <= 16'h0003; bram_D[57] <= 16'hFFF7; bram_D[58] <= 16'h000D; bram_D[59] <= 16'hFFF0; bram_D[60] <= 16'h0010; bram_D[61] <= 16'hFFF3; bram_D[62] <= 16'h0009; bram_D[63] <= 16'hFFFD;
        end else begin
            case(state)
                IDLE: begin
                    done <= 0;
                    if(start)
                        state <= MUL1;
                end
                MUL1: begin
                    if(mult_done) begin
                        // Capture the intermediate result into bram_B2 and into a register for the next multiplier
                        for(i = 0; i < 64; i = i + 1)
                            bram_B2[i] <= mat_out[i*16 +: 16];
                        inter_result <= mat_out;
                        state <= MUL2;
                    end
                end
                MUL2: begin
                    if(mult2_done) begin
                        // Write the final DCT result back to bram_X (overwriting X)
                        for(i = 0; i < 64; i = i + 1)
                            bram_X[i] <= final_result[i*16 +: 16];
                        state <= DONE;
                    end
                end
                DONE: begin
                    done <= 1;
                    state <= IDLE;
                end
            endcase
        end
    end

endmodule

jaskirat/DCT standalone_on_tb/iter3/iter3.srcs/sim_1/new/dct_test_tb.v
`timescale 1ns / 1ps

module tb_dct;
    reg clk;
    reg reset;
    reg start;
    wire done;
    integer i, j;

    // Instantiate the top-level DCT module
    dct_top dut (
        .clk(clk),
        .reset(reset),
        .start(start),
        .done(done)
    );

    // Clock generation: 100MHz
    always #5 clk = ~clk;

    initial begin
        clk = 0;
        reset = 1;
        start = 0;
        #20 reset = 0;
        
        // Initialize the input matrix X in bram_X to all ones (1.0 in Q8.8)
//        for(i = 0; i < 64; i = i + 1)
//            dut.bram_X[i] = 16'h0100;
dut.bram_X[0] = 16'h00A0; dut.bram_X[1] = 16'h0060; dut.bram_X[2] = 16'h0200; dut.bram_X[3] = 16'h0120; dut.bram_X[4] = 16'h01C0; dut.bram_X[5] = 16'h01C0; dut.bram_X[6] = 16'h0300; dut.bram_X[7] = 16'h02C0; dut.bram_X[8] = 16'h0080; dut.bram_X[9] = 16'h0140; dut.bram_X[10] = 16'h0180; dut.bram_X[11] = 16'h0140; dut.bram_X[12] = 16'h0200; dut.bram_X[13] = 16'h0200; dut.bram_X[14] = 16'h02A0; dut.bram_X[15] = 16'h0280; dut.bram_X[16] = 16'h0000; dut.bram_X[17] = 16'h00E0; dut.bram_X[18] = 16'h0100; dut.bram_X[19] = 16'h0180; dut.bram_X[20] = 16'h0260; dut.bram_X[21] = 16'h02A0; dut.bram_X[22] = 16'h0280; dut.bram_X[23] = 16'h0320; dut.bram_X[24] = 16'h00A0; dut.bram_X[25] = 16'h0140; dut.bram_X[26] = 16'h00C0; dut.bram_X[27] = 16'h01C0; dut.bram_X[28] = 16'h0200; dut.bram_X[29] = 16'h01A0; dut.bram_X[30] = 16'h01E0; dut.bram_X[31] = 16'h02A0; dut.bram_X[32] = 16'h00A0; dut.bram_X[33] = 16'h00C0; dut.bram_X[34] = 16'h00E0; dut.bram_X[35] = 16'h0180; dut.bram_X[36] = 16'h01A0; dut.bram_X[37] = 16'h0240; dut.bram_X[38] = 16'h0220; dut.bram_X[39] = 16'h0300; dut.bram_X[40] = 16'h1FE0; dut.bram_X[41] = 16'h00C0; dut.bram_X[42] = 16'h00C0; dut.bram_X[43] = 16'h0120; dut.bram_X[44] = 16'h0140; dut.bram_X[45] = 16'h01A0; dut.bram_X[46] = 16'h01C0; dut.bram_X[47] = 16'h0220; dut.bram_X[48] = 16'h00C0; dut.bram_X[49] = 16'h0040; dut.bram_X[50] = 16'h00A0; dut.bram_X[51] = 16'h01C0; dut.bram_X[52] = 16'h0180; dut.bram_X[53] = 16'h01A0; dut.bram_X[54] = 16'h01C0; dut.bram_X[55] = 16'h01C0; dut.bram_X[56] = 16'h0080; dut.bram_X[57] = 16'h0080; dut.bram_X[58] = 16'h01A0; dut.bram_X[59] = 16'h0120; dut.bram_X[60] = 16'h01C0; dut.bram_X[61] = 16'h01C0; dut.bram_X[62] = 16'h0140; dut.bram_X[63] = 16'h01E0; 


        
        #10 start = 1;
        #10 start = 0;
        
        wait(done);
        
        // Display the final DCT result (read from bram_X)
        $display("Final DCT Result (each element in Q8.8):");
        for(i = 0; i < 8; i = i + 1) begin
            for(j = 0; j < 8; j = j + 1) begin
                $write("%h ", dut.bram_X[i*8+j]);
            end
            $write("\n");
        end
        
        $finish;
    end

    initial begin
        $dumpfile("dct_waveform.vcd");
        $dumpvars(0, tb_dct);
    end

endmodule

jaskirat/DCT standalone_on_tb/iter3/iter3.sim/sim_1/behav/xsim/dct_waveform.vcd
$date
   Thu Apr 10 20:39:34 2025
$end

$version
  2024.2.1
  $dumpfile ("dct_waveform.vcd") 
$end

$timescale
  1ps
$end

$scope module tb_dct $end
$var reg 1 ! clk $end
$var reg 1 " reset $end
$var reg 1 # start $end
$var wire 1 $ done $end
$var integer 32 % i [31:0] $end
$var integer 32 & j [31:0] $end
$scope module dut $end
$var wire 1 ' clk $end
$var wire 1 ( reset $end
$var wire 1 ) start $end
$var reg 1 * done $end
$var reg 1024 + mat_A [1023:0] $end
$var reg 1024 , mat_B [1023:0] $end
$var wire 1024 - mat_out [1023:0] $end
$var wire 1 . mult_done $end
$var reg 1024 / inter_result [1023:0] $end
$var wire 1024 0 final_result [1023:0] $end
$var wire 1 1 mult2_done $end
$var reg 2 2 state [1:0] $end
$var integer 32 3 i [31:0] $end
$scope module mult1 $end
$var wire 1 ' clk $end
$var wire 1 ( reset $end
$var wire 1 4 enable $end
$var wire 1024 5 A [1023:0] $end
$var wire 1024 6 B [1023:0] $end
$var reg 1024 7 C [1023:0] $end
$var reg 1 8 done $end
$var reg 4 9 k [3:0] $end
$var reg 2 : state [1:0] $end
$var integer 32 ; i [31:0] $end
$var integer 32 < j [31:0] $end
$upscope $end
$scope module mult2 $end
$var wire 1 ' clk $end
$var wire 1 ( reset $end
$var wire 1 = enable $end
$var wire 1024 > A [1023:0] $end
$var wire 1024 ? B [1023:0] $end
$var reg 1024 @ C [1023:0] $end
$var reg 1 A done $end
$var reg 4 B k [3:0] $end
$var reg 2 C state [1:0] $end
$var integer 32 D i [31:0] $end
$var integer 32 E j [31:0] $end
$upscope $end
$upscope $end
$upscope $end
$enddefinitions $end

#0
$dumpvars
0!
1"
0#
0$
bx %
bx &
0'
1(
0)
0*
b1111111111111101000000000000100111111111111100110000000000010000111111111111000000000000000011011111111111110111000000000000001100000000000001101111111111110001000000000000111111111111111110101111111111111010000000000000111111111111111100010000000000000110111111111111011100000000000100001111111111111101111111111111001100000000000011010000000000000011111111111111000000000000000010010000000000001011111111111111010111111111111101010000000000001011000000000000101111111111111101011111111111110101000000000000101111111111111100110000000000000011000000000001000000000000000010011111111111110111111111111111000011111111111111010000000000001101000000000000111100000000000001101111111111111010111111111111000111111111111100011111111111111010000000000000011000000000000011111111111111110000111111111111001111111111111101111111111111111101000000000000001100000000000010010000000000001101000000000001000000000000000010110000000000001011000000000000101100000000000010110000000000001011000000000000101100000000000010110000000000001011 +
b1111111111111101000000000000100111111111111100110000000000010000111111111111000000000000000011011111111111110111000000000000001100000000000001101111111111110001000000000000111111111111111110101111111111111010000000000000111111111111111100010000000000000110111111111111011100000000000100001111111111111101111111111111001100000000000011010000000000000011111111111111000000000000000010010000000000001011111111111111010111111111111101010000000000001011000000000000101111111111111101011111111111110101000000000000101111111111111100110000000000000011000000000001000000000000000010011111111111110111111111111111000011111111111111010000000000001101000000000000111100000000000001101111111111111010111111111111000111111111111100011111111111111010000000000000011000000000000011111111111111110000111111111111001111111111111101111111111111111101000000000000001100000000000010010000000000001101000000000001000000000000000010110000000000001011000000000000101100000000000010110000000000001011000000000000101100000000000010110000000000001011 ,
bx -
0.
bx /
bx 0
01
b0 2
b1000000 3
04
b1111111111111101000000000000100111111111111100110000000000010000111111111111000000000000000011011111111111110111000000000000001100000000000001101111111111110001000000000000111111111111111110101111111111111010000000000000111111111111111100010000000000000110111111111111011100000000000100001111111111111101111111111111001100000000000011010000000000000011111111111111000000000000000010010000000000001011111111111111010111111111111101010000000000001011000000000000101111111111111101011111111111110101000000000000101111111111111100110000000000000011000000000001000000000000000010011111111111110111111111111111000011111111111111010000000000001101000000000000111100000000000001101111111111111010111111111111000111111111111100011111111111111010000000000000011000000000000011111111111111110000111111111111001111111111111101111111111111111101000000000000001100000000000010010000000000001101000000000001000000000000000010110000000000001011000000000000101100000000000010110000000000001011000000000000101100000000000010110000000000001011 5
b1111111111111101000000000000100111111111111100110000000000010000111111111111000000000000000011011111111111110111000000000000001100000000000001101111111111110001000000000000111111111111111110101111111111111010000000000000111111111111111100010000000000000110111111111111011100000000000100001111111111111101111111111111001100000000000011010000000000000011111111111111000000000000000010010000000000001011111111111111010111111111111101010000000000001011000000000000101111111111111101011111111111110101000000000000101111111111111100110000000000000011000000000001000000000000000010011111111111110111111111111111000011111111111111010000000000001101000000000000111100000000000001101111111111111010111111111111000111111111111100011111111111111010000000000000011000000000000011111111111111110000111111111111001111111111111101111111111111111101000000000000001100000000000010010000000000001101000000000001000000000000000010110000000000001011000000000000101100000000000010110000000000001011000000000000101100000000000010110000000000001011 6
bx 7
08
b0 9
b0 :
b1000 ;
b1000 <
0=
bx >
b1111111111111101000000000000100111111111111100110000000000010000111111111111000000000000000011011111111111110111000000000000001100000000000001101111111111110001000000000000111111111111111110101111111111111010000000000000111111111111111100010000000000000110111111111111011100000000000100001111111111111101111111111111001100000000000011010000000000000011111111111111000000000000000010010000000000001011111111111111010111111111111101010000000000001011000000000000101111111111111101011111111111110101000000000000101111111111111100110000000000000011000000000001000000000000000010011111111111110111111111111111000011111111111111010000000000001101000000000000111100000000000001101111111111111010111111111111000111111111111100011111111111111010000000000000011000000000000011111111111111110000111111111111001111111111111101111111111111111101000000000000001100000000000010010000000000001101000000000001000000000000000010110000000000001011000000000000101100000000000010110000000000001011000000000000101100000000000010110000000000001011 ?
bx @
0A
b0 B
b0 C
b1000 D
b1000 E
$end

#5000
1!
1'
b1000 ;
b1000 <
b1000 D
b1000 E

#10000
0!
0'

#15000
1!
1'
b1000 ;
b1000 <
b1000 D
b1000 E

#20000
0!
0"
0'
0(
b1000000 3

#25000
1!
1'

#30000
0!
1#
0'
1)

#35000
1!
1'
b111100000000000010100000000000001110000000000000111000000000000010010000000000001101000000000000010000000000000001000000000000001110000000000000111000000000000011010000000000001100000000000000111000000000000001010000000000000010000000000000011000000000000100010000000000001110000000000000110100000000000010100000000000001001000000000000011000000000000001100000000011111111000000000001100000000000000100010000000000010010000000000000110100000000000011000000000000000111000000000000011000000000000001010000000000010101000000000000111100000000000011010000000000010000000000000000111000000000000001100000000000001010000000000000010100000000000110010000000000010100000000000001010100000000000100110000000000001100000000000000100000000000000001110000000000000000000000000001010000000000000101010000000000010000000000000001000000000000000010100000000000001100000000000000101000000000000001000000000000010110000000000001100000000000000011100000000000001110000000000000100100000000000100000000000000000011000000000000010100000 ,
b1 2
b1000000 3
14
b111100000000000010100000000000001110000000000000111000000000000010010000000000001101000000000000010000000000000001000000000000001110000000000000111000000000000011010000000000001100000000000000111000000000000001010000000000000010000000000000011000000000000100010000000000001110000000000000110100000000000010100000000000001001000000000000011000000000000001100000000011111111000000000001100000000000000100010000000000010010000000000000110100000000000011000000000000000111000000000000011000000000000001010000000000010101000000000000111100000000000011010000000000010000000000000000111000000000000001100000000000001010000000000000010100000000000110010000000000010100000000000001010100000000000100110000000000001100000000000000100000000000000001110000000000000000000000000001010000000000000101010000000000010000000000000001000000000000000010100000000000001100000000000000101000000000000001000000000000010110000000000001100000000000000011100000000000001110000000000000100100000000000100000000000000000011000000000000010100000 6
b111100000000000010100000000000001110000000000000111000000000000010010000000000001101000000000000010000000000000001000000000000001110000000000000111000000000000011010000000000001100000000000000111000000000000001010000000000000010000000000000011000000000000100010000000000001110000000000000110100000000000010100000000000001001000000000000011000000000000001100000000011111111000000000001100000000000000100010000000000010010000000000000110100000000000011000000000000000111000000000000011000000000000001010000000000010101000000000000111100000000000011010000000000010000000000000000111000000000000001100000000000001010000000000000010100000000000110010000000000010100000000000001010100000000000100110000000000001100000000000000100000000000000001110000000000000000000000000001010000000000000101010000000000010000000000000001000000000000000010100000000000001100000000000000101000000000000001000000000000010110000000000001100000000000000011100000000000001110000000000000100100000000000100000000000000000011000000000000010100000 ?

#40000
0!
0#
0'
0)

#45000
1!
1'
b1 :

#50000
0!
0'

#55000
1!
1'
b10 :
b1000 ;
b1000 <

#60000
0!
0'

#65000
1!
1'
b1 9
b1000 ;
b1000 <

#70000
0!
0'

#75000
1!
1'
b10 9
b1000 ;
b1000 <

#80000
0!
0'

#85000
1!
1'
b11 9
b1000 ;
b1000 <

#90000
0!
0'

#95000
1!
1'
b100 9
b1000 ;
b1000 <

#100000
0!
0'

#105000
1!
1'
b101 9
b1000 ;
b1000 <

#110000
0!
0'

#115000
1!
1'
b110 9
b1000 ;
b1000 <

#120000
0!
0'

#125000
1!
1'
b111 9
b1000 ;
b1000 <

#130000
0!
0'

#135000
1!
1'
b0 9
b11 :
b1000 ;
b1000 <

#140000
0!
0'

#145000
1!
1'
b1110111000000000101100100000000100111010000000000100001000000000010101111111111111101001111111110000010111100110010001000000000010010001111111111111101000000000011100100000000000010011111111110100011000000000011001111111111110110010000111001010101111111111101000000000000000001101111111110100111000000000000001000000000011000111111111110100100111111111010111011111101001011000000000001000010111111111101111111111111110101000000000000000000111111111111010100000000011110011111111111101010111101010110111011111111111001000000000001010011111111111010010011111111010010011111111111001010111111111111101111111111101001110001000000000011111111110101100000000000001001001111111110110101111111111110101111111111100110100000000100000010111111110111001111111010001100110000000011111101000000010110101100000000011000000000000010001110111111111110110100000000100110100000000001101101111101101111111100000110110010100000010111001101000001010011111000000100111001100000001111010011000000110010001100000010000100000000110000110100 -
1.
b1110111000000000101100100000000100111010000000000100001000000000010101111111111111101001111111110000010111100110010001000000000010010001111111111111101000000000011100100000000000010011111111110100011000000000011001111111111110110010000111001010101111111111101000000000000000001101111111110100111000000000000001000000000011000111111111110100100111111111010111011111101001011000000000001000010111111111101111111111111110101000000000000000000111111111111010100000000011110011111111111101010111101010110111011111111111001000000000001010011111111111010010011111111010010011111111111001010111111111111101111111111101001110001000000000011111111110101100000000000001001001111111110110101111111111110101111111111100110100000000100000010111111110111001111111010001100110000000011111101000000010110101100000000011000000000000010001110111111111110110100000000100110100000000001101101111101101111111100000110110010100000010111001101000001010011111000000100111001100000001111010011000000110010001100000010000100000000110000110100 7
18
b0 :
b1000 ;
b1000 <

#150000
0!
0'

#155000
1!
1'
b1111111111111101000000000000100111111111111100110000000000010000111111111111000000000000000011011111111111110111000000000000001100000000000001101111111111110001000000000000111111111111111110101111111111111010000000000000111111111111111100010000000000000110111111111111011100000000000100001111111111111101111111111111001100000000000011010000000000000011111111111111000000000000000010010000000000001011111111111111010111111111111101010000000000001011000000000000101111111111111101011111111111110101000000000000101111111111111100110000000000000011000000000001000000000000000010011111111111110111111111111111000011111111111111010000000000001101000000000000111100000000000001101111111111111010111111111111000111111111111100011111111111111010000000000000011000000000000011111111111111110000111111111111001111111111111101111111111111111101000000000000001100000000000010010000000000001101000000000001000000000000000010110000000000001011000000000000101100000000000010110000000000001011000000000000101100000000000010110000000000001011 ,
b1110111000000000101100100000000100111010000000000100001000000000010101111111111111101001111111110000010111100110010001000000000010010001111111111111101000000000011100100000000000010011111111110100011000000000011001111111111110110010000111001010101111111111101000000000000000001101111111110100111000000000000001000000000011000111111111110100100111111111010111011111101001011000000000001000010111111111101111111111111110101000000000000000000111111111111010100000000011110011111111111101010111101010110111011111111111001000000000001010011111111111010010011111111010010011111111111001010111111111111101111111111101001110001000000000011111111110101100000000000001001001111111110110101111111111110101111111111100110100000000100000010111111110111001111111010001100110000000011111101000000010110101100000000011000000000000010001110111111111110110100000000100110100000000001101101111101101111111100000110110010100000010111001101000001010011111000000100111001100000001111010011000000110010001100000010000100000000110000110100 /
b10 2
b1000000 3
04
b1111111111111101000000000000100111111111111100110000000000010000111111111111000000000000000011011111111111110111000000000000001100000000000001101111111111110001000000000000111111111111111110101111111111111010000000000000111111111111111100010000000000000110111111111111011100000000000100001111111111111101111111111111001100000000000011010000000000000011111111111111000000000000000010010000000000001011111111111111010111111111111101010000000000001011000000000000101111111111111101011111111111110101000000000000101111111111111100110000000000000011000000000001000000000000000010011111111111110111111111111111000011111111111111010000000000001101000000000000111100000000000001101111111111111010111111111111000111111111111100011111111111111010000000000000011000000000000011111111111111110000111111111111001111111111111101111111111111111101000000000000001100000000000010010000000000001101000000000001000000000000000010110000000000001011000000000000101100000000000010110000000000001011000000000000101100000000000010110000000000001011 6
b1 :
1=
b1110111000000000101100100000000100111010000000000100001000000000010101111111111111101001111111110000010111100110010001000000000010010001111111111111101000000000011100100000000000010011111111110100011000000000011001111111111110110010000111001010101111111111101000000000000000001101111111110100111000000000000001000000000011000111111111110100100111111111010111011111101001011000000000001000010111111111101111111111111110101000000000000000000111111111111010100000000011110011111111111101010111101010110111011111111111001000000000001010011111111111010010011111111010010011111111111001010111111111111101111111111101001110001000000000011111111110101100000000000001001001111111110110101111111111110101111111111100110100000000100000010111111110111001111111010001100110000000011111101000000010110101100000000011000000000000010001110111111111110110100000000100110100000000001101101111101101111111100000110110010100000010111001101000001010011111000000100111001100000001111010011000000110010001100000010000100000000110000110100 >
b1111111111111101000000000000100111111111111100110000000000010000111111111111000000000000000011011111111111110111000000000000001100000000000001101111111111110001000000000000111111111111111110101111111111111010000000000000111111111111111100010000000000000110111111111111011100000000000100001111111111111101111111111111001100000000000011010000000000000011111111111111000000000000000010010000000000001011111111111111010111111111111101010000000000001011000000000000101111111111111101011111111111110101000000000000101111111111111100110000000000000011000000000001000000000000000010011111111111110111111111111111000011111111111111010000000000001101000000000000111100000000000001101111111111111010111111111111000111111111111100011111111111111010000000000000011000000000000011111111111111110000111111111111001111111111111101111111111111111101000000000000001100000000000010010000000000001101000000000001000000000000000010110000000000001011000000000000101100000000000010110000000000001011000000000000101100000000000010110000000000001011 ?

#160000
0!
0'

#165000
1!
1'
b10 :
b1000 ;
b1000 <
b1 C

#170000
0!
0'

#175000
1!
1'
b1 9
b1000 ;
b1000 <
b10 C
b1000 D
b1000 E

#180000
0!
0'

#185000
1!
1'
b10 9
b1000 ;
b1000 <
b1 B
b1000 D
b1000 E

#190000
0!
0'

#195000
1!
1'
b11 9
b1000 ;
b1000 <
b10 B
b1000 D
b1000 E

#200000
0!
0'

#205000
1!
1'
b100 9
b1000 ;
b1000 <
b11 B
b1000 D
b1000 E

#210000
0!
0'

#215000
1!
1'
b101 9
b1000 ;
b1000 <
b100 B
b1000 D
b1000 E

#220000
0!
0'

#225000
1!
1'
b110 9
b1000 ;
b1000 <
b101 B
b1000 D
b1000 E

#230000
0!
0'

#235000
1!
1'
b111 9
b1000 ;
b1000 <
b110 B
b1000 D
b1000 E

#240000
0!
0'

#245000
1!
1'
b0 9
b11 :
b1000 ;
b1000 <
b111 B
b1000 D
b1000 E

#250000
0!
0'

#255000
1!
1'
b10010100000000000100110100000000100101110000000000011111000000000010100111111111111101001111111110000000111100110010000100000000010100010000000000011001000000000011000000000000000000011111111110100010000000000010111111111111110110000000111001010100111111111101011100000000000010101111111111000100111111111111111000000000010110111111111110100011111111111010101011111101001010100000000001000101111111111110010111111111110101100000000000011100111111111111010100000000011100001111111111101010111101010110101111111111111001100000000001010100111111111010100111111111010010001111111111100111000000000000000011111111100111110001000000000001111111110101100100000000001001111111111110110100111111111111000111111111100101100000000100011110111111110111110011111010001011010000000011111111000000010110101100000000011000110000000010001011111111111111010000000000100100110000000010001001111101110000100000000110110010100000010111001111000001010011111000000100111010010000001111010000000000110010100100000010000001110000110001010000 -
b10010100000000000100110100000000100101110000000000011111000000000010100111111111111101001111111110000000111100110010000100000000010100010000000000011001000000000011000000000000000000011111111110100010000000000010111111111111110110000000111001010100111111111101011100000000000010101111111111000100111111111111111000000000010110111111111110100011111111111010101011111101001010100000000001000101111111111110010111111111110101100000000000011100111111111111010100000000011100001111111111101010111101010110101111111111111001100000000001010100111111111010100111111111010010001111111111100111000000000000000011111111100111110001000000000001111111110101100100000000001001111111111110110100111111111111000111111111100101100000000100011110111111110111110011111010001011010000000011111111000000010110101100000000011000110000000010001011111111111111010000000000100100110000000010001001111101110000100000000110110010100000010111001111000001010011111000000100111010010000001111010000000000110010100100000010000001110000110001010000 7
b0 :
b1000 ;
b1000 <
b0 B
b11 C
b1000 D
b1000 E

#260000
0!
0'

#265000
1!
1'
b1111111010110010111111011111001111111100100111111111101110110001111110101111101111111001111010011111100011001111111110111111101100000001100010110000001100010011000000111101101100000100110100100000010111011000000001101110010000000110111011000000010011111111111111111010011111111111001010111111111110010101111111110111000111111110110110111111111001111010111111101001001011111110110000011111111101000001111111100101000011111100111110011111110001101001111110110100100111111011000101101111101011000111111111000111100000000001100101100000001011111101000001010001101100000101010010010000011001001100000001111111010000000111111011100000010100000010000000000110011011111111011010001111111011100100111111011000001011111101011010011111110011111100111111010111101111111101101110001111111110111111111111100000000011111101011100111111110001110000111111000001100011111100001011101111101010011011111111100110000100000001001111010000001000101010000000101100001000000011111100010000001111100111000001001011011100000000011111100000111100011100 0
11
b1111111010110010111111011111001111111100100111111111101110110001111110101111101111111001111010011111100011001111111110111111101100000001100010110000001100010011000000111101101100000100110100100000010111011000000001101110010000000110111011000000010011111111111111111010011111111111001010111111111110010101111111110111000111111110110110111111111001111010111111101001001011111110110000011111111101000001111111100101000011111100111110011111110001101001111110110100100111111011000101101111101011000111111111000111100000000001100101100000001011111101000001010001101100000101010010010000011001001100000001111111010000000111111011100000010100000010000000000110011011111111011010001111111011100100111111011000001011111101011010011111110011111100111111010111101111111101101110001111111110111111111111100000000011111101011100111111110001110000111111000001100011111100001011101111101010011011111111100110000100000001001111010000001000101010000000101100001000000011111100010000001111100111000001001011011100000000011111100000111100011100 @
1A
b0 C
b1000 D
b1000 E

#270000
0!
0'

#275000
1!
1'
b11 2
b1000000 3
0=
b1 C

#280000
0!
0'

#285000
1!
1$
b1000 %
b1000 &
1'
1*
b0 2
b1000000 3
b10 C
b1000 D
b1000 E
