jaskirat/DCT standalone_on_tb/iter3/iter3.srcs/sources_1/new/dct_dsp_module.v
`timescale 1ns / 1ps

module matrix_mult_8x8_dsp #(
    parameter TRANSPOSE_B = 0
) (
    input clk,
    input reset,
    input enable,
    input [1023:0] A, // 8x8 matrix, each element 16-bit Q11.5
    input [1023:0] B,
    output reg [1023:0] C,
    output reg done
);

    // 2D arrays for the matrices (signed Q11.5 numbers)
    reg signed [15:0] matA [0:7][0:7];
    reg signed [15:0] matB [0:7][0:7];
    // 32-bit accumulators in Q22.10 format (result of Q11.5*Q11.5 multiplication)
    reg signed [31:0] accum [0:7][0:7];

    // Control signals and states
    reg [3:0] k;  // dot product index
    reg [1:0] state;
    localparam IDLE    = 2'b00,
               LOAD    = 2'b01,
               COMPUTE = 2'b10,
               DONE_ST = 2'b11;
    integer i, j;

    // Load matrices from the 1024-bit bus into 2D arrays
    always @(posedge clk) begin
        if (state == LOAD) begin
            for (i = 0; i < 8; i = i + 1) begin
                for (j = 0; j < 8; j = j + 1) begin
                    matA[i][j] <= A[(i*8+j)*16 +: 16];
                    matB[i][j] <= B[(i*8+j)*16 +: 16];
                end
            end
        end
    end

    // Main state machine using DSP slices for MAC operations
    always @(posedge clk or posedge reset) begin
        if (reset) begin
            state <= IDLE;
            done <= 0;
            k <= 0;
            for (i = 0; i < 8; i = i + 1)
                for (j = 0; j < 8; j = j + 1)
                    accum[i][j] <= 32'd0;
        end else begin
            case (state)
                IDLE: if (enable) state <= LOAD;
                LOAD: begin
                    state <= COMPUTE;
                    k <= 0;
                end
                COMPUTE: begin
                    // 64 parallel multiply-accumulate operations.
                    // When multiplying two Q11.5 numbers, the product is Q22.10.
                    for (i = 0; i < 8; i = i + 1) begin
                        for (j = 0; j < 8; j = j + 1) begin
                            (* use_dsp48 = "yes" *)
                            if (TRANSPOSE_B)
                                accum[i][j] <= accum[i][j] + (matA[i][k] * matB[j][k]);
                            else
                                accum[i][j] <= accum[i][j] + (matA[i][k] * matB[k][j]);
                        end
                    end
                    if (k == 7) begin
                        state <= DONE_ST;
                        k <= 0;
                    end else begin
                        k <= k + 1;
                    end
                end
                DONE_ST: begin
                    // Convert from Q22.10 to Q11.5 by discarding 5 fractional bits.
                    // Here we select bits [20:5] of the accumulator for each element.
                    for (i = 0; i < 8; i = i + 1) begin
                        for (j = 0; j < 8; j = j + 1) begin
                            C[(i*8+j)*16 +: 16] <= accum[i][j][20:5];
                        end
                    end
                    done <= 1;
                    state <= IDLE;
                end
            endcase
        end
    end

endmodule

jaskirat/DCT standalone_on_tb/iter3/iter3.srcs/sources_1/new/top_mod_dct.v
`timescale 1ns / 1ps

module dct_top (
    input clk,
    input reset,
    input start,
    output reg done
);
    // Behavioral BRAMs (64 words of 16 bits each)
    reg [15:0] bram_X [0:63];    // Input X (and final result overwritten here)
    reg [15:0] bram_B2 [0:63];   // Intermediate storage: result of D*X
    reg [15:0] bram_D [0:63];    // DCT coefficient ROM

    // Wires for connecting to the multiplier modules
    reg [1023:0] mat_A;
    reg [1023:0] mat_B;
    wire [1023:0] mat_out;
    wire mult_done;

    // For the second multiplication
    reg [1023:0] inter_result;
    wire [1023:0] final_result;
    wire mult2_done;

    // Top-level state machine
    reg [1:0] state;
    localparam IDLE = 2'b00,
               MUL1 = 2'b01,
               MUL2 = 2'b10,
               DONE  = 2'b11;
    integer i;

    // Instantiate multiplier for stage 1: D * X (normal multiplication)
    matrix_mult_8x8_dsp #(.TRANSPOSE_B(0)) mult1 (
        .clk(clk),
        .reset(reset),
        .enable(state == MUL1),
        .A(mat_A), // will carry D (from bram_D)
        .B(mat_B), // will carry X (from bram_X)
        .C(mat_out),
        .done(mult_done)
    );

    // Instantiate multiplier for stage 2: (D*X) * D^T 
    matrix_mult_8x8_dsp #(.TRANSPOSE_B(1)) mult2 (
        .clk(clk),
        .reset(reset),
        .enable(state == MUL2),
        .A(inter_result), // intermediate result from stage 1
        .B(mat_B),        // will carry D (from bram_D)
        .C(final_result),
        .done(mult2_done)
    );

    // Pack the contents of the coefficient ROM (bram_D) into a 1024-bit bus
    // This bus is used as the A operand for mult1.
    always @(*) begin
        for(i = 0; i < 64; i = i + 1)
            mat_A[i*16 +: 16] = bram_D[i];
    end

    // For the B operand: In stage MUL1 we use X (from bram_X), and in stage MUL2 we use D (from bram_D)
    always @(*) begin
        if(state == MUL1)
            for(i = 0; i < 64; i = i + 1)
                mat_B[i*16 +: 16] = bram_X[i];
        else
            for(i = 0; i < 64; i = i + 1)
                mat_B[i*16 +: 16] = bram_D[i];
    end

    // Top-level state machine: control the two multiplications and the memory transfers.
    always @(posedge clk or posedge reset) begin
        if(reset) begin
            state <= IDLE;
            done <= 0;
            // Initialize coefficient ROM (bram_D) with values.
            // In practice, replace these dummy values with the output of your Python script.
//            for(i = 0; i < 64; i = i + 1)
//                bram_D[i] <= 16'h0100; // dummy value = 1.0 (Q8.8); update with real DCT coefficients
bram_D[0] <= 16'h000B; bram_D[1] <= 16'h000B; bram_D[2] <= 16'h000B; bram_D[3] <= 16'h000B; bram_D[4] <= 16'h000B; bram_D[5] <= 16'h000B; bram_D[6] <= 16'h000B; bram_D[7] <= 16'h000B; bram_D[8] <= 16'h0010; bram_D[9] <= 16'h000D; bram_D[10] <= 16'h0009; bram_D[11] <= 16'h0003; bram_D[12] <= 16'hFFFD; bram_D[13] <= 16'hFFF7; bram_D[14] <= 16'hFFF3; bram_D[15] <= 16'hFFF0; bram_D[16] <= 16'h000F; bram_D[17] <= 16'h0006; bram_D[18] <= 16'hFFFA; bram_D[19] <= 16'hFFF1; bram_D[20] <= 16'hFFF1; bram_D[21] <= 16'hFFFA; bram_D[22] <= 16'h0006; bram_D[23] <= 16'h000F; bram_D[24] <= 16'h000D; bram_D[25] <= 16'hFFFD; bram_D[26] <= 16'hFFF0; bram_D[27] <= 16'hFFF7; bram_D[28] <= 16'h0009; bram_D[29] <= 16'h0010; bram_D[30] <= 16'h0003; bram_D[31] <= 16'hFFF3; bram_D[32] <= 16'h000B; bram_D[33] <= 16'hFFF5; bram_D[34] <= 16'hFFF5; bram_D[35] <= 16'h000B; bram_D[36] <= 16'h000B; bram_D[37] <= 16'hFFF5; bram_D[38] <= 16'hFFF5; bram_D[39] <= 16'h000B; bram_D[40] <= 16'h0009; bram_D[41] <= 16'hFFF0; bram_D[42] <= 16'h0003; bram_D[43] <= 16'h000D; bram_D[44] <= 16'hFFF3; bram_D[45] <= 16'hFFFD; bram_D[46] <= 16'h0010; bram_D[47] <= 16'hFFF7; bram_D[48] <= 16'h0006; bram_D[49] <= 16'hFFF1; bram_D[50] <= 16'h000F; bram_D[51] <= 16'hFFFA; bram_D[52] <= 16'hFFFA; bram_D[53] <= 16'h000F; bram_D[54] <= 16'hFFF1; bram_D[55] <= 16'h0006; bram_D[56] <= 16'h0003; bram_D[57] <= 16'hFFF7; bram_D[58] <= 16'h000D; bram_D[59] <= 16'hFFF0; bram_D[60] <= 16'h0010; bram_D[61] <= 16'hFFF3; bram_D[62] <= 16'h0009; bram_D[63] <= 16'hFFFD;
        end else begin
            case(state)
                IDLE: begin
                    done <= 0;
                    if(start)
                        state <= MUL1;
                end
                MUL1: begin
                    if(mult_done) begin
                        // Capture the intermediate result into bram_B2 and into a register for the next multiplier
                        for(i = 0; i < 64; i = i + 1)
                            bram_B2[i] <= mat_out[i*16 +: 16];
                        inter_result <= mat_out;
                        state <= MUL2;
                    end
                end
                MUL2: begin
                    if(mult2_done) begin
                        // Write the final DCT result back to bram_X (overwriting X)
                        for(i = 0; i < 64; i = i + 1)
                            bram_X[i] <= final_result[i*16 +: 16];
                        state <= DONE;
                    end
                end
                DONE: begin
                    done <= 1;
                    state <= IDLE;
                end
            endcase
        end
    end

endmodule

jaskirat/DCT standalone_on_tb/iter3/iter3.srcs/sim_1/new/dct_test_tb.v
`timescale 1ns / 1ps

module tb_dct;
    reg clk;
    reg reset;
    reg start;
    wire done;
    integer i, j;

    // Instantiate the top-level DCT module
    dct_top dut (
        .clk(clk),
        .reset(reset),
        .start(start),
        .done(done)
    );

    // Clock generation: 100MHz
    always #5 clk = ~clk;

    initial begin
        clk = 0;
        reset = 1;
        start = 0;
        #20 reset = 0;
        
        // Initialize the input matrix X in bram_X to all ones (1.0 in Q8.8)
//        for(i = 0; i < 64; i = i + 1)
//            dut.bram_X[i] = 16'h0100;
dut.bram_X[0] = 16'hFDC0; dut.bram_X[1] = 16'hFFE0; dut.bram_X[2] = 16'hF860; dut.bram_X[3] = 16'h0BA0; dut.bram_X[4] = 16'hFC60; dut.bram_X[5] = 16'h0CE0; dut.bram_X[6] = 16'hF240; dut.bram_X[7] = 16'hFA80; dut.bram_X[8] = 16'hFD60; dut.bram_X[9] = 16'hFF80; dut.bram_X[10] = 16'hF740; dut.bram_X[11] = 16'h0AE0; dut.bram_X[12] = 16'h0C40; dut.bram_X[13] = 16'hFC20; dut.bram_X[14] = 16'hFE40; dut.bram_X[15] = 16'hFFE0; dut.bram_X[16] = 16'hF600; dut.bram_X[17] = 16'hF940; dut.bram_X[18] = 16'hF420; dut.bram_X[19] = 16'h05E0; dut.bram_X[20] = 16'h0C20; dut.bram_X[21] = 16'hFE00; dut.bram_X[22] = 16'h0340; dut.bram_X[23] = 16'hFA80; dut.bram_X[24] = 16'hF9E0; dut.bram_X[25] = 16'h0FC0; dut.bram_X[26] = 16'h04A0; dut.bram_X[27] = 16'hFC20; dut.bram_X[28] = 16'h0A20; dut.bram_X[29] = 16'hF8A0; dut.bram_X[30] = 16'hF640; dut.bram_X[31] = 16'hF700; dut.bram_X[32] = 16'h0880; dut.bram_X[33] = 16'hF060; dut.bram_X[34] = 16'hFAA0; dut.bram_X[35] = 16'hF500; dut.bram_X[36] = 16'hF860; dut.bram_X[37] = 16'hFAA0; dut.bram_X[38] = 16'hF600; dut.bram_X[39] = 16'h0F20; dut.bram_X[40] = 16'h07C0; dut.bram_X[41] = 16'h0620; dut.bram_X[42] = 16'h0100; dut.bram_X[43] = 16'hFD40; dut.bram_X[44] = 16'hFC80; dut.bram_X[45] = 16'hFFA0; dut.bram_X[46] = 16'hFBA0; dut.bram_X[47] = 16'h06A0; dut.bram_X[48] = 16'hFCE0; dut.bram_X[49] = 16'hFC40; dut.bram_X[50] = 16'h0AC0; dut.bram_X[51] = 16'hFEE0; dut.bram_X[52] = 16'hFBE0; dut.bram_X[53] = 16'h0380; dut.bram_X[54] = 16'hF460; dut.bram_X[55] = 16'h0C40; dut.bram_X[56] = 16'hF9A0; dut.bram_X[57] = 16'h0520; dut.bram_X[58] = 16'h0080; dut.bram_X[59] = 16'hFD60; dut.bram_X[60] = 16'hF8C0; dut.bram_X[61] = 16'hF820; dut.bram_X[62] = 16'hF980; dut.bram_X[63] = 16'h0460; 

        
        #10 start = 1;
        #10 start = 0;
        
        wait(done);
        
        // Display the final DCT result (read from bram_X)
        $display("Final DCT Result (each element in Q8.8):");
        for(i = 0; i < 8; i = i + 1) begin
            for(j = 0; j < 8; j = j + 1) begin
                $write("%h ", dut.bram_X[i*8+j]);
            end
            $write("\n");
        end
        
        $finish;
    end

    initial begin
        $dumpfile("dct_waveform.vcd");
        $dumpvars(0, tb_dct);
    end

endmodule

jaskirat/DCT standalone_on_tb/iter3/iter3.sim/sim_1/behav/xsim/dct_waveform.vcd
$date
   Mon Apr  7 21:09:42 2025
$end
$version
  2019.2
$end
$timescale
  1ps
$end
$scope module tb_dct $end
$var reg 1 ! clk $end
$var reg 1 " reset $end
$var reg 1 # start $end
$var wire 1 $ done $end
$var integer 32 % i $end
$var integer 32 & j $end
$scope module dut $end
$var wire 1 ' clk $end
$var wire 1 ( reset $end
$var wire 1 ) start $end
$var reg 1 * done $end
$var reg 1024 + mat_A [1023:0] $end
$var reg 1024 , mat_B [1023:0] $end
$var wire 1024 - mat_out [1023:0] $end
$var wire 1 . mult_done $end
$var reg 1024 / inter_result [1023:0] $end
$var wire 1024 0 final_result [1023:0] $end
$var wire 1 1 mult2_done $end
$var reg 2 2 state [1:0] $end
$var integer 32 3 i $end
$var parameter 2 4 IDLE [1:0] $end
$var parameter 2 5 MUL1 [1:0] $end
$var parameter 2 6 MUL2 [1:0] $end
$var parameter 2 7 DONE [1:0] $end
$scope module mult1 $end
$var wire 1 ' clk $end
$var wire 1 ( reset $end
$var wire 1 8 enable $end
$var wire 1024 9 A [1023:0] $end
$var wire 1024 : B [1023:0] $end
$var reg 1024 ; C [1023:0] $end
$var reg 1 < done $end
$var reg 4 = k [3:0] $end
$var reg 2 > state [1:0] $end
$var integer 32 ? i $end
$var integer 32 @ j $end
$var parameter 32 A TRANSPOSE_B [31:0] $end
$var parameter 2 B IDLE [1:0] $end
$var parameter 2 C LOAD [1:0] $end
$var parameter 2 D COMPUTE [1:0] $end
$var parameter 2 E DONE_ST [1:0] $end
$upscope $end
$scope module mult2 $end
$var wire 1 ' clk $end
$var wire 1 ( reset $end
$var wire 1 F enable $end
$var wire 1024 G A [1023:0] $end
$var wire 1024 H B [1023:0] $end
$var reg 1024 I C [1023:0] $end
$var reg 1 J done $end
$var reg 4 K k [3:0] $end
$var reg 2 L state [1:0] $end
$var integer 32 M i $end
$var integer 32 N j $end
$var parameter 32 O TRANSPOSE_B [31:0] $end
$var parameter 2 P IDLE [1:0] $end
$var parameter 2 Q LOAD [1:0] $end
$var parameter 2 R COMPUTE [1:0] $end
$var parameter 2 S DONE_ST [1:0] $end
$upscope $end
$upscope $end
$upscope $end
$enddefinitions $end
#0
$dumpvars
0!
1"
0#
0$
bx %
bx &
0'
1(
0)
0*
b1111111111111101000000000000100111111111111100110000000000010000111111111111000000000000000011011111111111110111000000000000001100000000000001101111111111110001000000000000111111111111111110101111111111111010000000000000111111111111111100010000000000000110111111111111011100000000000100001111111111111101111111111111001100000000000011010000000000000011111111111111000000000000000010010000000000001011111111111111010111111111111101010000000000001011000000000000101111111111111101011111111111110101000000000000101111111111111100110000000000000011000000000001000000000000000010011111111111110111111111111111000011111111111111010000000000001101000000000000111100000000000001101111111111111010111111111111000111111111111100011111111111111010000000000000011000000000000011111111111111110000111111111111001111111111111101111111111111111101000000000000001100000000000010010000000000001101000000000001000000000000000010110000000000001011000000000000101100000000000010110000000000001011000000000000101100000000000010110000000000001011 +
b1111111111111101000000000000100111111111111100110000000000010000111111111111000000000000000011011111111111110111000000000000001100000000000001101111111111110001000000000000111111111111111110101111111111111010000000000000111111111111111100010000000000000110111111111111011100000000000100001111111111111101111111111111001100000000000011010000000000000011111111111111000000000000000010010000000000001011111111111111010111111111111101010000000000001011000000000000101111111111111101011111111111110101000000000000101111111111111100110000000000000011000000000001000000000000000010011111111111110111111111111111000011111111111111010000000000001101000000000000111100000000000001101111111111111010111111111111000111111111111100011111111111111010000000000000011000000000000011111111111111110000111111111111001111111111111101111111111111111101000000000000001100000000000010010000000000001101000000000001000000000000000010110000000000001011000000000000101100000000000010110000000000001011000000000000101100000000000010110000000000001011 ,
bx -
0.
bx /
bx 0
01
b0 2
b1000000 3
b0 4
b1 5
b10 6
b11 7
08
b1111111111111101000000000000100111111111111100110000000000010000111111111111000000000000000011011111111111110111000000000000001100000000000001101111111111110001000000000000111111111111111110101111111111111010000000000000111111111111111100010000000000000110111111111111011100000000000100001111111111111101111111111111001100000000000011010000000000000011111111111111000000000000000010010000000000001011111111111111010111111111111101010000000000001011000000000000101111111111111101011111111111110101000000000000101111111111111100110000000000000011000000000001000000000000000010011111111111110111111111111111000011111111111111010000000000001101000000000000111100000000000001101111111111111010111111111111000111111111111100011111111111111010000000000000011000000000000011111111111111110000111111111111001111111111111101111111111111111101000000000000001100000000000010010000000000001101000000000001000000000000000010110000000000001011000000000000101100000000000010110000000000001011000000000000101100000000000010110000000000001011 9
b1111111111111101000000000000100111111111111100110000000000010000111111111111000000000000000011011111111111110111000000000000001100000000000001101111111111110001000000000000111111111111111110101111111111111010000000000000111111111111111100010000000000000110111111111111011100000000000100001111111111111101111111111111001100000000000011010000000000000011111111111111000000000000000010010000000000001011111111111111010111111111111101010000000000001011000000000000101111111111111101011111111111110101000000000000101111111111111100110000000000000011000000000001000000000000000010011111111111110111111111111111000011111111111111010000000000001101000000000000111100000000000001101111111111111010111111111111000111111111111100011111111111111010000000000000011000000000000011111111111111110000111111111111001111111111111101111111111111111101000000000000001100000000000010010000000000001101000000000001000000000000000010110000000000001011000000000000101100000000000010110000000000001011000000000000101100000000000010110000000000001011 :
bx ;
0<
b0 =
b0 >
b1000 ?
b1000 @
b0 A
b0 B
b1 C
b10 D
b11 E
0F
bx G
b1111111111111101000000000000100111111111111100110000000000010000111111111111000000000000000011011111111111110111000000000000001100000000000001101111111111110001000000000000111111111111111110101111111111111010000000000000111111111111111100010000000000000110111111111111011100000000000100001111111111111101111111111111001100000000000011010000000000000011111111111111000000000000000010010000000000001011111111111111010111111111111101010000000000001011000000000000101111111111111101011111111111110101000000000000101111111111111100110000000000000011000000000001000000000000000010011111111111110111111111111111000011111111111111010000000000001101000000000000111100000000000001101111111111111010111111111111000111111111111100011111111111111010000000000000011000000000000011111111111111110000111111111111001111111111111101111111111111111101000000000000001100000000000010010000000000001101000000000001000000000000000010110000000000001011000000000000101100000000000010110000000000001011000000000000101100000000000010110000000000001011 H
bx I
0J
b0 K
b0 L
b1000 M
b1000 N
b1 O
b0 P
b1 Q
b10 R
b11 S
$end
#5000
1!
1'
b1000 ?
b1000 @
b1000 M
b1000 N
#10000
0!
0'
#15000
1!
1'
b1000 ?
b1000 @
b1000 M
b1000 N
#20000
0!
0"
0'
0(
b1111111111111101000000000000100111111111111100110000000000010000111111111111000000000000000011011111111111110111000000000000001100000000000001101111111111110001000000000000111111111111111110101111111111111010000000000000111111111111111100010000000000000110111111111111011100000000000100001111111111111101111111111111001100000000000011010000000000000011111111111111000000000000000010010000000000001011111111111111010111111111111101010000000000001011000000000000101111111111111101011111111111110101000000000000101111111111111100110000000000000011000000000001000000000000000010011111111111110111111111111111000011111111111111010000000000001101000000000000111100000000000001101111111111111010111111111111000111111111111100011111111111111010000000000000011000000000000011111111111111110000111111111111001111111111111101111111111111111101000000000000001100000000000010010000000000001101000000000001000000000000000010110000000000001011000000000000101100000000000010110000000000001011000000000000101100000000000010110000000000001011 ,
b1000000 3
#25000
1!
1'
#30000
0!
1#
0'
1)
#35000
1!
1'
b10001100000111110011000000011111000001000001111100011000000111111010110000000000000100000000000010100100000111110011010000000001100010000001111010001100000000000111000000011111011111000001111111011100000000010101100000011111100010000001111110011100000000001101010000011111011101000001111111110100000111111001000000011111101010000000000000100000000000001100010000000000111110000000000111100100000111101100000000011111010101000001111100001100000111101010000000011111010101000001111000001100000000010001000000011110111000000001111011001000000111110001010000000001010001000001111110000100000000001001010000000001111110000001111100111100000111110101000000000000011010000001111111000000000000011000010000000000101111000001111010000100000111110010100000011110110000000001111111111100000111111100100000011111100001000000000110001000000000010101110000011110111010000001111111110000000111111010110000011111010100000001111001001000000000011001110000011111100011000000000101110100000111110000110000011111111111000001111110111000000 ,
b1 2
b1000000 3
18
b10001100000111110011000000011111000001000001111100011000000111111010110000000000000100000000000010100100000111110011010000000001100010000001111010001100000000000111000000011111011111000001111111011100000000010101100000011111100010000001111110011100000000001101010000011111011101000001111111110100000111111001000000011111101010000000000000100000000000001100010000000000111110000000000111100100000111101100000000011111010101000001111100001100000111101010000000011111010101000001111000001100000000010001000000011110111000000001111011001000000111110001010000000001010001000001111110000100000000001001010000000001111110000001111100111100000111110101000000000000011010000001111111000000000000011000010000000000101111000001111010000100000111110010100000011110110000000001111111111100000111111100100000011111100001000000000110001000000000010101110000011110111010000001111111110000000111111010110000011111010100000001111001001000000000011001110000011111100011000000000101110100000111110000110000011111111111000001111110111000000 :
b10001100000111110011000000011111000001000001111100011000000111111010110000000000000100000000000010100100000111110011010000000001100010000001111010001100000000000111000000011111011111000001111111011100000000010101100000011111100010000001111110011100000000001101010000011111011101000001111111110100000111111001000000011111101010000000000000100000000000001100010000000000111110000000000111100100000111101100000000011111010101000001111100001100000111101010000000011111010101000001111000001100000000010001000000011110111000000001111011001000000111110001010000000001010001000001111110000100000000001001010000000001111110000001111100111100000111110101000000000000011010000001111111000000000000011000010000000000101111000001111010000100000111110010100000011110110000000001111111111100000111111100100000011111100001000000000110001000000000010101110000011110111010000001111111110000000111111010110000011111010100000001111001001000000000011001110000011111100011000000000101110100000111110000110000011111111111000001111110111000000 H
#40000
0!
0#
0'
0)
#45000
1!
1'
b1 >
#50000
0!
0'
#55000
1!
1'
b10 >
b1000 ?
b1000 @
#60000
0!
0'
#65000
1!
1'
b1 =
b1000 ?
b1000 @
#70000
0!
0'
#75000
1!
1'
b10 =
b1000 ?
b1000 @
#80000
0!
0'
#85000
1!
1'
b11 =
b1000 ?
b1000 @
#90000
0!
0'
#95000
1!
1'
b100 =
b1000 ?
b1000 @
#100000
0!
0'
#105000
1!
1'
b101 =
b1000 ?
b1000 @
#110000
0!
0'
#115000
1!
1'
b110 =
b1000 ?
b1000 @
#120000
0!
0'
#125000
1!
1'
b111 =
b1000 ?
b1000 @
#130000
0!
0'
#135000
1!
1'
b0 =
b11 >
b1000 ?
b1000 @
#140000
0!
0'
#145000
1!
1'
b100110110001111111111000010000000100010111001111100100110101111111011110011111111010011111101110100110101101000000000101100111111001011111000000010110100110000000100110010011111101101110100000000101011111111110001100010100000010100111011111111110010100111110000111100111111001110101110000100010001111000000011000001000000001101101100000101001010010000010000111000011111001010011101111110100101010111101110011110011111110010010001111011101011101111110011000111000000000010110000000001101110000000000001001101000001001111111111111100000111111000010100111111111110011001000101111111001011001000000100010011111111011001011010000111010011110111111101010101011111101011110000000100010110010111110011010001100001100011011111111111101101101000000011001101111111010001100001111000001011101000000101000111000000110101111000000111010000110000011110001100011110001010101011111111000000100111110111110011100000110010001101110110101000100111111000110010000000010111000010000001001101000111110100011111000000000000101101111101100011010 -
1.
b100110110001111111111000010000000100010111001111100100110101111111011110011111111010011111101110100110101101000000000101100111111001011111000000010110100110000000100110010011111101101110100000000101011111111110001100010100000010100111011111111110010100111110000111100111111001110101110000100010001111000000011000001000000001101101100000101001010010000010000111000011111001010011101111110100101010111101110011110011111110010010001111011101011101111110011000111000000000010110000000001101110000000000001001101000001001111111111111100000111111000010100111111111110011001000101111111001011001000000100010011111111011001011010000111010011110111111101010101011111101011110000000100010110010111110011010001100001100011011111111111101101101000000011001101111111010001100001111000001011101000000101000111000000110101111000000111010000110000011110001100011110001010101011111111000000100111110111110011100000110010001101110110101000100111111000110010000000010111000010000001001101000111110100011111000000000000101101111101100011010 ;
1<
b0 >
b1000 ?
b1000 @
#150000
0!
0'
#155000
1!
1'
b1111111111111101000000000000100111111111111100110000000000010000111111111111000000000000000011011111111111110111000000000000001100000000000001101111111111110001000000000000111111111111111110101111111111111010000000000000111111111111111100010000000000000110111111111111011100000000000100001111111111111101111111111111001100000000000011010000000000000011111111111111000000000000000010010000000000001011111111111111010111111111111101010000000000001011000000000000101111111111111101011111111111110101000000000000101111111111111100110000000000000011000000000001000000000000000010011111111111110111111111111111000011111111111111010000000000001101000000000000111100000000000001101111111111111010111111111111000111111111111100011111111111111010000000000000011000000000000011111111111111110000111111111111001111111111111101111111111111111101000000000000001100000000000010010000000000001101000000000001000000000000000010110000000000001011000000000000101100000000000010110000000000001011000000000000101100000000000010110000000000001011 ,
b100110110001111111111000010000000100010111001111100100110101111111011110011111111010011111101110100110101101000000000101100111111001011111000000010110100110000000100110010011111101101110100000000101011111111110001100010100000010100111011111111110010100111110000111100111111001110101110000100010001111000000011000001000000001101101100000101001010010000010000111000011111001010011101111110100101010111101110011110011111110010010001111011101011101111110011000111000000000010110000000001101110000000000001001101000001001111111111111100000111111000010100111111111110011001000101111111001011001000000100010011111111011001011010000111010011110111111101010101011111101011110000000100010110010111110011010001100001100011011111111111101101101000000011001101111111010001100001111000001011101000000101000111000000110101111000000111010000110000011110001100011110001010101011111111000000100111110111110011100000110010001101110110101000100111111000110010000000010111000010000001001101000111110100011111000000000000101101111101100011010 /
b10 2
b1000000 3
08
b1111111111111101000000000000100111111111111100110000000000010000111111111111000000000000000011011111111111110111000000000000001100000000000001101111111111110001000000000000111111111111111110101111111111111010000000000000111111111111111100010000000000000110111111111111011100000000000100001111111111111101111111111111001100000000000011010000000000000011111111111111000000000000000010010000000000001011111111111111010111111111111101010000000000001011000000000000101111111111111101011111111111110101000000000000101111111111111100110000000000000011000000000001000000000000000010011111111111110111111111111111000011111111111111010000000000001101000000000000111100000000000001101111111111111010111111111111000111111111111100011111111111111010000000000000011000000000000011111111111111110000111111111111001111111111111101111111111111111101000000000000001100000000000010010000000000001101000000000001000000000000000010110000000000001011000000000000101100000000000010110000000000001011000000000000101100000000000010110000000000001011 :
b1 >
1F
b100110110001111111111000010000000100010111001111100100110101111111011110011111111010011111101110100110101101000000000101100111111001011111000000010110100110000000100110010011111101101110100000000101011111111110001100010100000010100111011111111110010100111110000111100111111001110101110000100010001111000000011000001000000001101101100000101001010010000010000111000011111001010011101111110100101010111101110011110011111110010010001111011101011101111110011000111000000000010110000000001101110000000000001001101000001001111111111111100000111111000010100111111111110011001000101111111001011001000000100010011111111011001011010000111010011110111111101010101011111101011110000000100010110010111110011010001100001100011011111111111101101101000000011001101111111010001100001111000001011101000000101000111000000110101111000000111010000110000011110001100011110001010101011111111000000100111110111110011100000110010001101110110101000100111111000110010000000010111000010000001001101000111110100011111000000000000101101111101100011010 G
b1111111111111101000000000000100111111111111100110000000000010000111111111111000000000000000011011111111111110111000000000000001100000000000001101111111111110001000000000000111111111111111110101111111111111010000000000000111111111111111100010000000000000110111111111111011100000000000100001111111111111101111111111111001100000000000011010000000000000011111111111111000000000000000010010000000000001011111111111111010111111111111101010000000000001011000000000000101111111111111101011111111111110101000000000000101111111111111100110000000000000011000000000001000000000000000010011111111111110111111111111111000011111111111111010000000000001101000000000000111100000000000001101111111111111010111111111111000111111111111100011111111111111010000000000000011000000000000011111111111111110000111111111111001111111111111101111111111111111101000000000000001100000000000010010000000000001101000000000001000000000000000010110000000000001011000000000000101100000000000010110000000000001011000000000000101100000000000010110000000000001011 H
#160000
0!
0'
#165000
1!
1'
b10 >
b1000 ?
b1000 @
b1 L
#170000
0!
0'
#175000
1!
1'
b1 =
b1000 ?
b1000 @
b10 L
b1000 M
b1000 N
#180000
0!
0'
#185000
1!
1'
b10 =
b1000 ?
b1000 @
b1 K
b1000 M
b1000 N
#190000
0!
0'
#195000
1!
1'
b11 =
b1000 ?
b1000 @
b10 K
b1000 M
b1000 N
#200000
0!
0'
#205000
1!
1'
b100 =
b1000 ?
b1000 @
b11 K
b1000 M
b1000 N
#210000
0!
0'
#215000
1!
1'
b101 =
b1000 ?
b1000 @
b100 K
b1000 M
b1000 N
#220000
0!
0'
#225000
1!
1'
b110 =
b1000 ?
b1000 @
b101 K
b1000 M
b1000 N
#230000
0!
0'
#235000
1!
1'
b111 =
b1000 ?
b1000 @
b110 K
b1000 M
b1000 N
#240000
0!
0'
#245000
1!
1'
b0 =
b11 >
b1000 ?
b1000 @
b111 K
b1000 M
b1000 N
#250000
0!
0'
#255000
1!
1'
b100111001110111111110111100000000100010101101111100100110011111111011110010111111010011111101110100110101011000000000101100011111001100001010000010111000010000000100101101111111101101100100000000101011110111110001100000100000010100111001111111110010011111110001000000011111001110110110000100010101100000000010111111000000001101011100000101001010001000010000110110011111001010011001111110100101101111101110100001011111110010010101111011101111001111110011000111000000000010011110000001101110000000000001001011100001010000000011111100001000000000010101000010011110011001000011111111001110110000000100010110011111011001001010000111010011100111111101010101111111101011110110000100010110001111110011010100100001100011010111111111110001001000000011010010011111010001010101111000001011111000000101000111000000110101111110000111010000011000011110001111111110001010011101111111000100000111110111111000000000110010001101110110101000110111111000110010000000010111001000000001001100101111110100100010000000000000011011111101100110110 -
b100111001110111111110111100000000100010101101111100100110011111111011110010111111010011111101110100110101011000000000101100011111001100001010000010111000010000000100101101111111101101100100000000101011110111110001100000100000010100111001111111110010011111110001000000011111001110110110000100010101100000000010111111000000001101011100000101001010001000010000110110011111001010011001111110100101101111101110100001011111110010010101111011101111001111110011000111000000000010011110000001101110000000000001001011100001010000000011111100001000000000010101000010011110011001000011111111001110110000000100010110011111011001001010000111010011100111111101010101111111101011110110000100010110001111110011010100100001100011010111111111110001001000000011010010011111010001010101111000001011111000000101000111000000110101111110000111010000011000011110001111111110001010011101111111000100000111110111111000000000110010001101110110101000110111111000110010000000010111001000000001001100101111110100100010000000000000011011111101100110110 ;
b0 >
b1000 ?
b1000 @
b0 K
b11 L
b1000 M
b1000 N
#260000
0!
0'
