jaskirat/DCT standalone_on_tb/iter3/iter3.srcs/sources_1/new/MAX_DSP.v
`timescale 1ns / 1ps

module matrix_mult_8x8_max_dsp (
    input clk,
    input reset,
    input enable,
    input [1023:0] A,  // 8x8 of 16-bit Q8.8
    input [1023:0] B,
    output reg [1023:0] C,
    output reg done
);

// Internal registers
reg signed [15:0] matA [0:7][0:7];
reg signed [15:0] matB [0:7][0:7];
reg signed [31:0] accum [0:7][0:7];  // Q16.16 accumulators

// Control signals
reg [3:0] k;  // Dot product index
reg [1:0] state;

// States
localparam IDLE    = 2'b00;
localparam LOAD    = 2'b01;
localparam COMPUTE = 2'b10;
localparam DONE_ST = 2'b11;
integer i, j;

// Load matrices
always @(posedge clk) begin
    if (state == LOAD) begin
        for (i=0; i<8; i=i+1) begin
            for (j=0; j<8; j=j+1) begin
                matA[i][j] <= A[(i*8+j)*16 +:16];
                matB[i][j] <= B[(i*8+j)*16 +:16];
            end
        end
    end
end

// Compute using 64 parallel multipliers
always @(posedge clk or posedge reset) begin
    if (reset) begin
        state <= IDLE;
        done <= 0;
        k <= 0;
        for(i=0; i<8; i=i+1) begin
            for(j=0; j<8; j=j+1) begin
                accum[i][j] <= 32'd0;
            end
        end
    end else case(state)
        IDLE: if(enable) state <= LOAD;
        
        LOAD: begin
            state <= COMPUTE;
            k <= 0;
        end
        
        COMPUTE: begin
            // Parallel MAC operations (64 multipliers)
            for(i=0; i<8; i=i+1) begin
                for(j=0; j<8; j=j+1) begin
                    (* use_dsp48 = "yes" *)  // Force DSP usage
                    accum[i][j] <= accum[i][j] + (matA[i][k] * matB[k][j]);
                end
            end
            
            k <= (k == 7) ? 0 : k + 1;
            state <= (k == 7) ? DONE_ST : COMPUTE;
        end
        
        DONE_ST: begin
            // Convert Q16.16 to Q8.8
            for(i=0; i<8; i=i+1) begin
                for(j=0; j<8; j=j+1) begin
                    C[(i*8+j)*16 +:16] <= accum[i][j][23:8];
                end
            end
            done <= 1;
            state <= IDLE;
        end
    endcase
end

endmodule

jaskirat/DCT standalone_on_tb/iter3/iter3.srcs/sim_1/new/dsp_max_tb.v
`timescale 1ns / 1ps

module tb_matrix_max_dsp;

reg clk;
reg reset;
reg enable;
reg [1023:0] A, B;
wire [1023:0] C;
wire done;

matrix_mult_8x8_max_dsp dut (
    .clk(clk),
    .reset(reset),
    .enable(enable),
    .A(A),
    .B(B),
    .C(C),
    .done(done)
);

always #0.1 clk = ~clk;  // 100MHz clock
integer i, j;
initial begin
    clk = 0;
    reset = 1;
    enable = 0;
    A = 1024'd0;
    B = 1024'd0;
    
    // Initialize all elements to 1.0 (Q8.8)
    #100 reset = 0;
    for(i=0; i<8; i=i+1) begin
        for(j=0; j<8; j=j+1) begin
            A[(i*8+j)*16 +:16] = 16'h0100;  // 1.0
            B[(i*8+j)*16 +:16] = 16'h0100;
        end
    end
    
    #10 enable = 1;
    wait(done);
    
    // Verify results
    $display("Result Matrix:");
    for(i=0; i<8; i=i+1) begin
        $write("Row %0d: ", i);
        for(j=0; j<8; j=j+1) begin
            $write("%h ", C[(i*8+j)*16 +:16]);
        end
        $write("\n");
    end
    
    if(C[15:0] === 16'h0800)  // Check for 8.0 (0x0800)
        $display("Test PASSED");
    else
        $display("Test FAILED");
    
    $finish;
end

initial begin
    $dumpfile("waveform.vcd");
    $dumpvars(0, tb_matrix_max_dsp);
end

endmodule

jaskirat/DCT standalone_on_tb/iter3/iter3.sim/sim_1/behav/xsim/waveform.vcd
$date
   Fri Apr  4 21:58:48 2025
$end
$version
  2019.2
$end
$timescale
  1ps
$end
$scope module tb_matrix_max_dsp $end
$var reg 1 ! clk $end
$var reg 1 " reset $end
$var reg 1 # enable $end
$var reg 1024 $ A [1023:0] $end
$var reg 1024 % B [1023:0] $end
$var wire 1024 & C [1023:0] $end
$var wire 1 ' done $end
$var integer 32 ( i $end
$var integer 32 ) j $end
$scope module dut $end
$var wire 1 * clk $end
$var wire 1 + reset $end
$var wire 1 , enable $end
$var wire 1024 - A [1023:0] $end
$var wire 1024 . B [1023:0] $end
$var reg 1024 / C [1023:0] $end
$var reg 1 0 done $end
$var reg 4 1 k [3:0] $end
$var reg 2 2 state [1:0] $end
$var integer 32 3 i $end
$var integer 32 4 j $end
$var parameter 2 5 IDLE [1:0] $end
$var parameter 2 6 LOAD [1:0] $end
$var parameter 2 7 COMPUTE [1:0] $end
$var parameter 2 8 DONE_ST [1:0] $end
$upscope $end
$upscope $end
$enddefinitions $end
#0
$dumpvars
0!
1"
0#
b0 $
b0 %
bx &
0'
bx (
bx )
0*
1+
0,
b0 -
b0 .
bx /
00
b0 1
b0 2
b1000 3
b1000 4
b0 5
b1 6
b10 7
b11 8
$end
#100
1!
1*
b1000 3
b1000 4
#200
0!
0*
#300
1!
1*
b1000 3
b1000 4
#400
0!
0*
#500
1!
1*
b1000 3
b1000 4
#600
0!
0*
#700
1!
1*
b1000 3
b1000 4
#800
0!
0*
#900
1!
1*
b1000 3
b1000 4
#1000
0!
0*
#1100
1!
1*
b1000 3
b1000 4
#1200
0!
0*
#1300
1!
1*
b1000 3
b1000 4
#1400
0!
0*
#1500
1!
1*
b1000 3
b1000 4
#1600
0!
0*
#1700
1!
1*
b1000 3
b1000 4
#1800
0!
0*
#1900
1!
1*
b1000 3
b1000 4
#2000
0!
0*
#2100
1!
1*
b1000 3
b1000 4
#2200
0!
0*
#2300
1!
1*
b1000 3
b1000 4
#2400
0!
0*
#2500
1!
1*
b1000 3
b1000 4
#2600
0!
0*
#2700
1!
1*
b1000 3
b1000 4
#2800
0!
0*
#2900
1!
1*
b1000 3
b1000 4
#3000
0!
0*
#3100
1!
1*
b1000 3
b1000 4
#3200
0!
0*
#3300
1!
1*
b1000 3
b1000 4
#3400
0!
0*
#3500
1!
1*
b1000 3
b1000 4
#3600
0!
0*
#3700
1!
1*
b1000 3
b1000 4
#3800
0!
0*
#3900
1!
1*
b1000 3
b1000 4
#4000
0!
0*
#4100
1!
1*
b1000 3
b1000 4
#4200
0!
0*
#4300
1!
1*
b1000 3
b1000 4
#4400
0!
0*
#4500
1!
1*
b1000 3
b1000 4
#4600
0!
0*
#4700
1!
1*
b1000 3
b1000 4
#4800
0!
0*
#4900
1!
1*
b1000 3
b1000 4
#5000
0!
0*
#5100
1!
1*
b1000 3
b1000 4
#5200
0!
0*
#5300
1!
1*
b1000 3
b1000 4
#5400
0!
0*
#5500
1!
1*
b1000 3
b1000 4
#5600
0!
0*
#5700
1!
1*
b1000 3
b1000 4
#5800
0!
0*
#5900
1!
1*
b1000 3
b1000 4
#6000
0!
0*
#6100
1!
1*
b1000 3
b1000 4
#6200
0!
0*
#6300
1!
1*
b1000 3
b1000 4
#6400
0!
0*
#6500
1!
1*
b1000 3
b1000 4
#6600
0!
0*
#6700
1!
1*
b1000 3
b1000 4
#6800
0!
0*
#6900
1!
1*
b1000 3
b1000 4
#7000
0!
0*
#7100
1!
1*
b1000 3
b1000 4
#7200
0!
0*
#7300
1!
1*
b1000 3
b1000 4
#7400
0!
0*
#7500
1!
1*
b1000 3
b1000 4
#7600
0!
0*
#7700
1!
1*
b1000 3
b1000 4
#7800
0!
0*
#7900
1!
1*
b1000 3
b1000 4
#8000
0!
0*
#8100
1!
1*
b1000 3
b1000 4
#8200
0!
0*
#8300
1!
1*
b1000 3
b1000 4
#8400
0!
0*
#8500
1!
1*
b1000 3
b1000 4
#8600
0!
0*
#8700
1!
1*
b1000 3
b1000 4
#8800
0!
0*
#8900
1!
1*
b1000 3
b1000 4
#9000
0!
0*
#9100
1!
1*
b1000 3
b1000 4
#9200
0!
0*
#9300
1!
1*
b1000 3
b1000 4
#9400
0!
0*
#9500
1!
1*
b1000 3
b1000 4
#9600
0!
0*
#9700
1!
1*
b1000 3
b1000 4
#9800
0!
0*
#9900
1!
1*
b1000 3
b1000 4
#10000
0!
0*
#10100
1!
1*
b1000 3
b1000 4
#10200
0!
0*
#10300
1!
1*
b1000 3
b1000 4
#10400
0!
0*
#10500
1!
1*
b1000 3
b1000 4
#10600
0!
0*
#10700
1!
1*
b1000 3
b1000 4
#10800
0!
0*
#10900
1!
1*
b1000 3
b1000 4
#11000
0!
0*
#11100
1!
1*
b1000 3
b1000 4
#11200
0!
0*
#11300
1!
1*
b1000 3
b1000 4
#11400
0!
0*
#11500
1!
1*
b1000 3
b1000 4
#11600
0!
0*
#11700
1!
1*
b1000 3
b1000 4
#11800
0!
0*
#11900
1!
1*
b1000 3
b1000 4
#12000
0!
0*
#12100
1!
1*
b1000 3
b1000 4
#12200
0!
0*
#12300
1!
1*
b1000 3
b1000 4
#12400
0!
0*
#12500
1!
1*
b1000 3
b1000 4
#12600
0!
0*
#12700
1!
1*
b1000 3
b1000 4
#12800
0!
0*
#12900
1!
1*
b1000 3
b1000 4
#13000
0!
0*
#13100
1!
1*
b1000 3
b1000 4
#13200
0!
0*
#13300
1!
1*
b1000 3
b1000 4
#13400
0!
0*
#13500
1!
1*
b1000 3
b1000 4
#13600
0!
0*
#13700
1!
1*
b1000 3
b1000 4
#13800
0!
0*
#13900
1!
1*
b1000 3
b1000 4
#14000
0!
0*
#14100
1!
1*
b1000 3
b1000 4
#14200
0!
0*
#14300
1!
1*
b1000 3
b1000 4
#14400
0!
0*
#14500
1!
1*
b1000 3
b1000 4
#14600
0!
0*
#14700
1!
1*
b1000 3
b1000 4
#14800
0!
0*
#14900
1!
1*
b1000 3
b1000 4
#15000
0!
0*
#15100
1!
1*
b1000 3
b1000 4
#15200
0!
0*
#15300
1!
1*
b1000 3
b1000 4
#15400
0!
0*
#15500
1!
1*
b1000 3
b1000 4
#15600
0!
0*
#15700
1!
1*
b1000 3
b1000 4
#15800
0!
0*
#15900
1!
1*
b1000 3
b1000 4
#16000
0!
0*
#16100
1!
1*
b1000 3
b1000 4
#16200
0!
0*
#16300
1!
1*
b1000 3
b1000 4
#16400
0!
0*
#16500
1!
1*
b1000 3
b1000 4
#16600
0!
0*
#16700
1!
1*
b1000 3
b1000 4
#16800
0!
0*
#16900
1!
1*
b1000 3
b1000 4
#17000
0!
0*
#17100
1!
1*
b1000 3
b1000 4
#17200
0!
0*
#17300
1!
1*
b1000 3
b1000 4
#17400
0!
0*
#17500
1!
1*
b1000 3
b1000 4
#17600
0!
0*
#17700
1!
1*
b1000 3
b1000 4
#17800
0!
0*
#17900
1!
1*
b1000 3
b1000 4
#18000
0!
0*
#18100
1!
1*
b1000 3
b1000 4
#18200
0!
0*
#18300
1!
1*
b1000 3
b1000 4
#18400
0!
0*
#18500
1!
1*
b1000 3
b1000 4
#18600
0!
0*
#18700
1!
1*
b1000 3
b1000 4
#18800
0!
0*
#18900
1!
1*
b1000 3
b1000 4
#19000
0!
0*
#19100
1!
1*
b1000 3
b1000 4
#19200
0!
0*
#19300
1!
1*
b1000 3
b1000 4
#19400
0!
0*
#19500
1!
1*
b1000 3
b1000 4
#19600
0!
0*
#19700
1!
1*
b1000 3
b1000 4
#19800
0!
0*
#19900
1!
1*
b1000 3
b1000 4
#20000
0!
0*
#20100
1!
1*
b1000 3
b1000 4
#20200
0!
0*
#20300
1!
1*
b1000 3
b1000 4
#20400
0!
0*
#20500
1!
1*
b1000 3
b1000 4
#20600
0!
0*
#20700
1!
1*
b1000 3
b1000 4
#20800
0!
0*
#20900
1!
1*
b1000 3
b1000 4
#21000
0!
0*
#21100
1!
1*
b1000 3
b1000 4
#21200
0!
0*
#21300
1!
1*
b1000 3
b1000 4
#21400
0!
0*
#21500
1!
1*
b1000 3
b1000 4
#21600
0!
0*
#21700
1!
1*
b1000 3
b1000 4
#21800
0!
0*
#21900
1!
1*
b1000 3
b1000 4
#22000
0!
0*
#22100
1!
1*
b1000 3
b1000 4
#22200
0!
0*
#22300
1!
1*
b1000 3
b1000 4
#22400
0!
0*
#22500
1!
1*
b1000 3
b1000 4
#22600
0!
0*
#22700
1!
1*
b1000 3
b1000 4
#22800
0!
0*
#22900
1!
1*
b1000 3
b1000 4
#23000
0!
0*
#23100
1!
1*
b1000 3
b1000 4
#23200
0!
0*
#23300
1!
1*
b1000 3
b1000 4
#23400
0!
0*
#23500
1!
1*
b1000 3
b1000 4
#23600
0!
0*
#23700
1!
1*
b1000 3
b1000 4
#23800
0!
0*
#23900
1!
1*
b1000 3
b1000 4
#24000
0!
0*
#24100
1!
1*
b1000 3
b1000 4
#24200
0!
0*
#24300
1!
1*
b1000 3
b1000 4
#24400
0!
0*
#24500
1!
1*
b1000 3
b1000 4
#24600
0!
0*
#24700
1!
1*
b1000 3
b1000 4
#24800
0!
0*
#24900
1!
1*
b1000 3
b1000 4
#25000
0!
0*
#25100
1!
1*
b1000 3
b1000 4
#25200
0!
0*
#25300
1!
1*
b1000 3
b1000 4
#25400
0!
0*
#25500
1!
1*
b1000 3
b1000 4
#25600
0!
0*
#25700
1!
1*
b1000 3
b1000 4
#25800
0!
0*
#25900
1!
1*
b1000 3
b1000 4
#26000
0!
0*
#26100
1!
1*
b1000 3
b1000 4
#26200
0!
0*
#26300
1!
1*
b1000 3
b1000 4
#26400
0!
0*
#26500
1!
1*
b1000 3
b1000 4
#26600
0!
0*
#26700
1!
1*
b1000 3
b1000 4
#26800
0!
0*
#26900
1!
1*
b1000 3
b1000 4
#27000
0!
0*
#27100
1!
1*
b1000 3
b1000 4
#27200
0!
0*
#27300
1!
1*
b1000 3
b1000 4
#27400
0!
0*
#27500
1!
1*
b1000 3
b1000 4
#27600
0!
0*
#27700
1!
1*
b1000 3
b1000 4
#27800
0!
0*
#27900
1!
1*
b1000 3
b1000 4
#28000
0!
0*
#28100
1!
1*
b1000 3
b1000 4
#28200
0!
0*
#28300
1!
1*
b1000 3
b1000 4
#28400
0!
0*
#28500
1!
1*
b1000 3
b1000 4
#28600
0!
0*
#28700
1!
1*
b1000 3
b1000 4
#28800
0!
0*
#28900
1!
1*
b1000 3
b1000 4
#29000
0!
0*
#29100
1!
1*
b1000 3
b1000 4
#29200
0!
0*
#29300
1!
1*
b1000 3
b1000 4
#29400
0!
0*
#29500
1!
1*
b1000 3
b1000 4
#29600
0!
0*
#29700
1!
1*
b1000 3
b1000 4
#29800
0!
0*
#29900
1!
1*
b1000 3
b1000 4
#30000
0!
0*
#30100
1!
1*
b1000 3
b1000 4
#30200
0!
0*
#30300
1!
1*
b1000 3
b1000 4
#30400
0!
0*
#30500
1!
1*
b1000 3
b1000 4
#30600
0!
0*
#30700
1!
1*
b1000 3
b1000 4
#30800
0!
0*
#30900
1!
1*
b1000 3
b1000 4
#31000
0!
0*
#31100
1!
1*
b1000 3
b1000 4
#31200
0!
0*
#31300
1!
1*
b1000 3
b1000 4
#31400
0!
0*
#31500
1!
1*
b1000 3
b1000 4
#31600
0!
0*
#31700
1!
1*
b1000 3
b1000 4
#31800
0!
0*
#31900
1!
1*
b1000 3
b1000 4
#32000
0!
0*
#32100
1!
1*
b1000 3
b1000 4
#32200
0!
0*
#32300
1!
1*
b1000 3
b1000 4
#32400
0!
0*
#32500
1!
1*
b1000 3
b1000 4
#32600
0!
0*
#32700
1!
1*
b1000 3
b1000 4
#32800
0!
0*
#32900
1!
1*
b1000 3
b1000 4
#33000
0!
0*
#33100
1!
1*
b1000 3
b1000 4
#33200
0!
0*
#33300
1!
1*
b1000 3
b1000 4
#33400
0!
0*
#33500
1!
1*
b1000 3
b1000 4
#33600
0!
0*
#33700
1!
1*
b1000 3
b1000 4
#33800
0!
0*
#33900
1!
1*
b1000 3
b1000 4
#34000
0!
0*
#34100
1!
1*
b1000 3
b1000 4
#34200
0!
0*
#34300
1!
1*
b1000 3
b1000 4
#34400
0!
0*
#34500
1!
1*
b1000 3
b1000 4
#34600
0!
0*
#34700
1!
1*
b1000 3
b1000 4
#34800
0!
0*
#34900
1!
1*
b1000 3
b1000 4
#35000
0!
0*
#35100
1!
1*
b1000 3
b1000 4
#35200
0!
0*
#35300
1!
1*
b1000 3
b1000 4
#35400
0!
0*
#35500
1!
1*
b1000 3
b1000 4
#35600
0!
0*
#35700
1!
1*
b1000 3
b1000 4
#35800
0!
0*
#35900
1!
1*
b1000 3
b1000 4
#36000
0!
0*
#36100
1!
1*
b1000 3
b1000 4
#36200
0!
0*
#36300
1!
1*
b1000 3
b1000 4
#36400
0!
0*
#36500
1!
1*
b1000 3
b1000 4
#36600
0!
0*
#36700
1!
1*
b1000 3
b1000 4
#36800
0!
0*
#36900
1!
1*
b1000 3
b1000 4
#37000
0!
0*
#37100
1!
1*
b1000 3
b1000 4
#37200
0!
0*
#37300
1!
1*
b1000 3
b1000 4
#37400
0!
0*
#37500
1!
1*
b1000 3
b1000 4
#37600
0!
0*
#37700
1!
1*
b1000 3
b1000 4
#37800
0!
0*
#37900
1!
1*
b1000 3
b1000 4
#38000
0!
0*
#38100
1!
1*
b1000 3
b1000 4
#38200
0!
0*
#38300
1!
1*
b1000 3
b1000 4
#38400
0!
0*
#38500
1!
1*
b1000 3
b1000 4
#38600
0!
0*
#38700
1!
1*
b1000 3
b1000 4
#38800
0!
0*
#38900
1!
1*
b1000 3
b1000 4
#39000
0!
0*
#39100
1!
1*
b1000 3
b1000 4
#39200
0!
0*
#39300
1!
1*
b1000 3
b1000 4
#39400
0!
0*
#39500
1!
1*
b1000 3
b1000 4
#39600
0!
0*
#39700
1!
1*
b1000 3
b1000 4
#39800
0!
0*
#39900
1!
1*
b1000 3
b1000 4
#40000
0!
0*
#40100
1!
1*
b1000 3
b1000 4
#40200
0!
0*
#40300
1!
1*
b1000 3
b1000 4
#40400
0!
0*
#40500
1!
1*
b1000 3
b1000 4
#40600
0!
0*
#40700
1!
1*
b1000 3
b1000 4
#40800
0!
0*
#40900
1!
1*
b1000 3
b1000 4
#41000
0!
0*
#41100
1!
1*
b1000 3
b1000 4
#41200
0!
0*
#41300
1!
1*
b1000 3
b1000 4
#41400
0!
0*
#41500
1!
1*
b1000 3
b1000 4
#41600
0!
0*
#41700
1!
1*
b1000 3
b1000 4
#41800
0!
0*
#41900
1!
1*
b1000 3
b1000 4
#42000
0!
0*
#42100
1!
1*
b1000 3
b1000 4
#42200
0!
0*
#42300
1!
1*
b1000 3
b1000 4
#42400
0!
0*
#42500
1!
1*
b1000 3
b1000 4
#42600
0!
0*
#42700
1!
1*
b1000 3
b1000 4
#42800
0!
0*
#42900
1!
1*
b1000 3
b1000 4
#43000
0!
0*
#43100
1!
1*
b1000 3
b1000 4
#43200
0!
0*
#43300
1!
1*
b1000 3
b1000 4
#43400
0!
0*
#43500
1!
1*
b1000 3
b1000 4
#43600
0!
0*
#43700
1!
1*
b1000 3
b1000 4
#43800
0!
0*
#43900
1!
1*
b1000 3
b1000 4
#44000
0!
0*
#44100
1!
1*
b1000 3
b1000 4
#44200
0!
0*
#44300
1!
1*
b1000 3
b1000 4
#44400
0!
0*
#44500
1!
1*
b1000 3
b1000 4
#44600
0!
0*
#44700
1!
1*
b1000 3
b1000 4
#44800
0!
0*
#44900
1!
1*
b1000 3
b1000 4
#45000
0!
0*
#45100
1!
1*
b1000 3
b1000 4
#45200
0!
0*
#45300
1!
1*
b1000 3
b1000 4
#45400
0!
0*
#45500
1!
1*
b1000 3
b1000 4
#45600
0!
0*
#45700
1!
1*
b1000 3
b1000 4
#45800
0!
0*
#45900
1!
1*
b1000 3
b1000 4
#46000
0!
0*
#46100
1!
1*
b1000 3
b1000 4
#46200
0!
0*
#46300
1!
1*
b1000 3
b1000 4
#46400
0!
0*
#46500
1!
1*
b1000 3
b1000 4
#46600
0!
0*
#46700
1!
1*
b1000 3
b1000 4
#46800
0!
0*
#46900
1!
1*
b1000 3
b1000 4
#47000
0!
0*
#47100
1!
1*
b1000 3
b1000 4
#47200
0!
0*
#47300
1!
1*
b1000 3
b1000 4
#47400
0!
0*
#47500
1!
1*
b1000 3
b1000 4
#47600
0!
0*
#47700
1!
1*
b1000 3
b1000 4
#47800
0!
0*
#47900
1!
1*
b1000 3
b1000 4
#48000
0!
0*
#48100
1!
1*
b1000 3
b1000 4
#48200
0!
0*
#48300
1!
1*
b1000 3
b1000 4
#48400
0!
0*
#48500
1!
1*
b1000 3
b1000 4
#48600
0!
0*
#48700
1!
1*
b1000 3
b1000 4
#48800
0!
0*
#48900
1!
1*
b1000 3
b1000 4
#49000
0!
0*
#49100
1!
1*
b1000 3
b1000 4
#49200
0!
0*
#49300
1!
1*
b1000 3
b1000 4
#49400
0!
0*
#49500
1!
1*
b1000 3
b1000 4
#49600
0!
0*
#49700
1!
1*
b1000 3
b1000 4
#49800
0!
0*
#49900
1!
1*
b1000 3
b1000 4
#50000
0!
0*
#50100
1!
1*
b1000 3
b1000 4
#50200
0!
0*
#50300
1!
1*
b1000 3
b1000 4
#50400
0!
0*
#50500
1!
1*
b1000 3
b1000 4
#50600
0!
0*
#50700
1!
1*
b1000 3
b1000 4
#50800
0!
0*
#50900
1!
1*
b1000 3
b1000 4
#51000
0!
0*
#51100
1!
1*
b1000 3
b1000 4
#51200
0!
0*
#51300
1!
1*
b1000 3
b1000 4
#51400
0!
0*
#51500
1!
1*
b1000 3
b1000 4
#51600
0!
0*
#51700
1!
1*
b1000 3
b1000 4
#51800
0!
0*
#51900
1!
1*
b1000 3
b1000 4
#52000
0!
0*
#52100
1!
1*
b1000 3
b1000 4
#52200
0!
0*
#52300
1!
1*
b1000 3
b1000 4
#52400
0!
0*
#52500
1!
1*
b1000 3
b1000 4
#52600
0!
0*
#52700
1!
1*
b1000 3
b1000 4
#52800
0!
0*
#52900
1!
1*
b1000 3
b1000 4
#53000
0!
0*
#53100
1!
1*
b1000 3
b1000 4
#53200
0!
0*
#53300
1!
1*
b1000 3
b1000 4
#53400
0!
0*
#53500
1!
1*
b1000 3
b1000 4
#53600
0!
0*
#53700
1!
1*
b1000 3
b1000 4
#53800
0!
0*
#53900
1!
1*
b1000 3
b1000 4
#54000
0!
0*
#54100
1!
1*
b1000 3
b1000 4
#54200
0!
0*
#54300
1!
1*
b1000 3
b1000 4
#54400
0!
0*
#54500
1!
1*
b1000 3
b1000 4
#54600
0!
0*
#54700
1!
1*
b1000 3
b1000 4
#54800
0!
0*
#54900
1!
1*
b1000 3
b1000 4
#55000
0!
0*
#55100
1!
1*
b1000 3
b1000 4
#55200
0!
0*
#55300
1!
1*
b1000 3
b1000 4
#55400
0!
0*
#55500
1!
1*
b1000 3
b1000 4
#55600
0!
0*
#55700
1!
1*
b1000 3
b1000 4
#55800
0!
0*
#55900
1!
1*
b1000 3
b1000 4
#56000
0!
0*
#56100
1!
1*
b1000 3
b1000 4
#56200
0!
0*
#56300
1!
1*
b1000 3
b1000 4
#56400
0!
0*
#56500
1!
1*
b1000 3
b1000 4
#56600
0!
0*
#56700
1!
1*
b1000 3
b1000 4
#56800
0!
0*
#56900
1!
1*
b1000 3
b1000 4
#57000
0!
0*
#57100
1!
1*
b1000 3
b1000 4
#57200
0!
0*
#57300
1!
1*
b1000 3
b1000 4
#57400
0!
0*
#57500
1!
1*
b1000 3
b1000 4
#57600
0!
0*
#57700
1!
1*
b1000 3
b1000 4
#57800
0!
0*
#57900
1!
1*
b1000 3
b1000 4
#58000
0!
0*
#58100
1!
1*
b1000 3
b1000 4
#58200
0!
0*
#58300
1!
1*
b1000 3
b1000 4
#58400
0!
0*
#58500
1!
1*
b1000 3
b1000 4
#58600
0!
0*
#58700
1!
1*
b1000 3
b1000 4
#58800
0!
0*
#58900
1!
1*
b1000 3
b1000 4
#59000
0!
0*
#59100
1!
1*
b1000 3
b1000 4
#59200
0!
0*
#59300
1!
1*
b1000 3
b1000 4
#59400
0!
0*
#59500
1!
1*
b1000 3
b1000 4
#59600
0!
0*
#59700
1!
1*
b1000 3
b1000 4
#59800
0!
0*
#59900
1!
1*
b1000 3
b1000 4
#60000
0!
0*
#60100
1!
1*
b1000 3
b1000 4
#60200
0!
0*
#60300
1!
1*
b1000 3
b1000 4
#60400
0!
0*
#60500
1!
1*
b1000 3
b1000 4
#60600
0!
0*
#60700
1!
1*
b1000 3
b1000 4
#60800
0!
0*
#60900
1!
1*
b1000 3
b1000 4
#61000
0!
0*
#61100
1!
1*
b1000 3
b1000 4
#61200
0!
0*
#61300
1!
1*
b1000 3
b1000 4
#61400
0!
0*
#61500
1!
1*
b1000 3
b1000 4
#61600
0!
0*
#61700
1!
1*
b1000 3
b1000 4
#61800
0!
0*
#61900
1!
1*
b1000 3
b1000 4
#62000
0!
0*
#62100
1!
1*
b1000 3
b1000 4
#62200
0!
0*
#62300
1!
1*
b1000 3
b1000 4
#62400
0!
0*
#62500
1!
1*
b1000 3
b1000 4
#62600
0!
0*
#62700
1!
1*
b1000 3
b1000 4
#62800
0!
0*
#62900
1!
1*
b1000 3
b1000 4
#63000
0!
0*
#63100
1!
1*
b1000 3
b1000 4
#63200
0!
0*
#63300
1!
1*
b1000 3
b1000 4
#63400
0!
0*
#63500
1!
1*
b1000 3
b1000 4
#63600
0!
0*
#63700
1!
1*
b1000 3
b1000 4
#63800
0!
0*
#63900
1!
1*
b1000 3
b1000 4
#64000
0!
0*
#64100
1!
1*
b1000 3
b1000 4
#64200
0!
0*
#64300
1!
1*
b1000 3
b1000 4
#64400
0!
0*
#64500
1!
1*
b1000 3
b1000 4
#64600
0!
0*
#64700
1!
1*
b1000 3
b1000 4
#64800
0!
0*
#64900
1!
1*
b1000 3
b1000 4
#65000
0!
0*
#65100
1!
1*
b1000 3
b1000 4
#65200
0!
0*
#65300
1!
1*
b1000 3
b1000 4
#65400
0!
0*
#65500
1!
1*
b1000 3
b1000 4
#65600
0!
0*
#65700
1!
1*
b1000 3
b1000 4
#65800
0!
0*
#65900
1!
1*
b1000 3
b1000 4
#66000
0!
0*
#66100
1!
1*
b1000 3
b1000 4
#66200
0!
0*
#66300
1!
1*
b1000 3
b1000 4
#66400
0!
0*
#66500
1!
1*
b1000 3
b1000 4
#66600
0!
0*
#66700
1!
1*
b1000 3
b1000 4
#66800
0!
0*
#66900
1!
1*
b1000 3
b1000 4
#67000
0!
0*
#67100
1!
1*
b1000 3
b1000 4
#67200
0!
0*
#67300
1!
1*
b1000 3
b1000 4
#67400
0!
0*
#67500
1!
1*
b1000 3
b1000 4
#67600
0!
0*
#67700
1!
1*
b1000 3
b1000 4
#67800
0!
0*
#67900
1!
1*
b1000 3
b1000 4
#68000
0!
0*
#68100
1!
1*
b1000 3
b1000 4
#68200
0!
0*
#68300
1!
1*
b1000 3
b1000 4
#68400
0!
0*
#68500
1!
1*
b1000 3
b1000 4
#68600
0!
0*
#68700
1!
1*
b1000 3
b1000 4
#68800
0!
0*
#68900
1!
1*
b1000 3
b1000 4
#69000
0!
0*
#69100
1!
1*
b1000 3
b1000 4
#69200
0!
0*
#69300
1!
1*
b1000 3
b1000 4
#69400
0!
0*
#69500
1!
1*
b1000 3
b1000 4
#69600
0!
0*
#69700
1!
1*
b1000 3
b1000 4
#69800
0!
0*
#69900
1!
1*
b1000 3
b1000 4
#70000
0!
0*
#70100
1!
1*
b1000 3
b1000 4
#70200
0!
0*
#70300
1!
1*
b1000 3
b1000 4
#70400
0!
0*
#70500
1!
1*
b1000 3
b1000 4
#70600
0!
0*
#70700
1!
1*
b1000 3
b1000 4
#70800
0!
0*
#70900
1!
1*
b1000 3
b1000 4
#71000
0!
0*
#71100
1!
1*
b1000 3
b1000 4
#71200
0!
0*
#71300
1!
1*
b1000 3
b1000 4
#71400
0!
0*
#71500
1!
1*
b1000 3
b1000 4
#71600
0!
0*
#71700
1!
1*
b1000 3
b1000 4
#71800
0!
0*
#71900
1!
1*
b1000 3
b1000 4
#72000
0!
0*
#72100
1!
1*
b1000 3
b1000 4
#72200
0!
0*
#72300
1!
1*
b1000 3
b1000 4
#72400
0!
0*
#72500
1!
1*
b1000 3
b1000 4
#72600
0!
0*
#72700
1!
1*
b1000 3
b1000 4
#72800
0!
0*
#72900
1!
1*
b1000 3
b1000 4
#73000
0!
0*
#73100
1!
1*
b1000 3
b1000 4
#73200
0!
0*
#73300
1!
1*
b1000 3
b1000 4
#73400
0!
0*
#73500
1!
1*
b1000 3
b1000 4
#73600
0!
0*
#73700
1!
1*
b1000 3
b1000 4
#73800
0!
0*
#73900
1!
1*
b1000 3
b1000 4
#74000
0!
0*
#74100
1!
1*
b1000 3
b1000 4
#74200
0!
0*
#74300
1!
1*
b1000 3
b1000 4
#74400
0!
0*
#74500
1!
1*
b1000 3
b1000 4
#74600
0!
0*
#74700
1!
1*
b1000 3
b1000 4
#74800
0!
0*
#74900
1!
1*
b1000 3
b1000 4
#75000
0!
0*
#75100
1!
1*
b1000 3
b1000 4
#75200
0!
0*
#75300
1!
1*
b1000 3
b1000 4
#75400
0!
0*
#75500
1!
1*
b1000 3
b1000 4
#75600
0!
0*
#75700
1!
1*
b1000 3
b1000 4
#75800
0!
0*
#75900
1!
1*
b1000 3
b1000 4
#76000
0!
0*
#76100
1!
1*
b1000 3
b1000 4
#76200
0!
0*
#76300
1!
1*
b1000 3
b1000 4
#76400
0!
0*
#76500
1!
1*
b1000 3
b1000 4
#76600
0!
0*
#76700
1!
1*
b1000 3
b1000 4
#76800
0!
0*
#76900
1!
1*
b1000 3
b1000 4
#77000
0!
0*
#77100
1!
1*
b1000 3
b1000 4
#77200
0!
0*
#77300
1!
1*
b1000 3
b1000 4
#77400
0!
0*
#77500
1!
1*
b1000 3
b1000 4
#77600
0!
0*
#77700
1!
1*
b1000 3
b1000 4
#77800
0!
0*
#77900
1!
1*
b1000 3
b1000 4
#78000
0!
0*
#78100
1!
1*
b1000 3
b1000 4
#78200
0!
0*
#78300
1!
1*
b1000 3
b1000 4
#78400
0!
0*
#78500
1!
1*
b1000 3
b1000 4
#78600
0!
0*
#78700
1!
1*
b1000 3
b1000 4
#78800
0!
0*
#78900
1!
1*
b1000 3
b1000 4
